{
  "hi": [
    {
      "id": 1,
      "question": "आपको एक एसएमएस मिला जिसमें कहा गया है कि आपका बैंक खाता निलंबित है और आपको इसे सत्यापित करने के लिए एक लिंक पर क्लिक करना होगा। आप क्या करेंगे?",
      "options": [
        "संदेश को अनदेखा करें और सीधे अपने बैंक ऐप की जाँच करें",
        "इसे तुरंत ठीक करने के लिए लिंक पर क्लिक करें",
        "विवरण मांगते हुए एसएमएस का जवाब दें"
      ],
      "correct_index": 0,
      "category": "banking",
      "explanation": "बैंक कभी भी एसएमएस में एक लिंक के माध्यम से आपके खाते की पुष्टि करने के लिए नहीं कहेगा। हमेशा आधिकारिक ऐप या वेबसाइट का उपयोग करें।"
    },
    {
      "id": 2,
      "question": "किसी लिंक के हमलावर होने का एक संकेत क्या है?",
      "options": [
        "यह 'https://' का उपयोग करता है",
        "डोमेन नाम थोड़ा गलत लिखा गया है (जैसे, g00gle.com)",
        "यह बहुत लंबा है"
      ],
      "correct_index": 1,
      "category": "link_safety",
      "explanation": "टाइपोस्क्वाटिंग एक सामान्य रणनीति है जहां हमलावर वास्तविक लोगों जैसे दिखने वाले डोमेन का उपयोग करते हैं लेकिन जिसमें सूक्ष्म त्रुटियां होती हैं।"
    },
    {
      "id": 3,
      "question": "एक एसएमएस आपको अपना ईमेल और फोन नंबर देने के लिए $1,000 का उपहार कार्ड प्रदान करता है। क्या यह सुरक्षित है?",
      "options": [
        "हाँ, कंपनियां अक्सर दान देती हैं",
        "केवल अगर संदेश में आपका पूरा नाम शामिल है",
        "नहीं, अगर यह सच में बहुत अच्छा लगता है, तो यह शायद सच नहीं है"
      ],
      "correct_index": 2,
      "category": "personal_info",
      "explanation": "अप्रत्याशित पुरस्कार फिशिंग के पारंपरिक लURES हैं जो आपकी व्यक्तिगत जानकारी चोरी करने के लिए डिज़ाइन किए गए हैं।"
    },
    {
      "id": 4,
      "question": "एक कॉलर दावा करता है कि वे आपके बैंक के 'फ्रॉड विभाग' से हैं और आपके खाते को सुरक्षित करने के लिए ओटीपी मांगते हैं। क्या आप देंगे?",
      "options": [
        "नहीं, बैंक कभी भी फोन पर ओटीपी नहीं मांगते",
        "हाँ, वे मेरी मदद करने की कोशिश कर रहे हैं",
        "केवल अगर वे पहले से ही मेरा खाता नंबर जानते हैं"
      ],
      "correct_index": 0,
      "category": "banking",
      "explanation": "एक ओटीपी (वन-टाइम पासवर्ड) केवल आपकी आँखों के लिए है। बैंक कभी भी कॉल पर इसके लिए नहीं पूछेगा।"
    },
    {
      "id": 5,
      "question": "एक मित्र आपको व्हाट्सएप पर एक लिंक भेजता है जो 'मुफ्त आईफोन दान' के लिए है जिसके लिए आपको इसे 10 मित्रों को आगे बढ़ाना होगा। यह क्या होने की संभावना है?",
      "options": [
        "एक वायरल मार्केटिंग अभियान",
        "संपर्क विवरण एकत्र करने के लिए एक फिशिंग स्केम",
        "एक बड़े निगम का एक वास्तविक उपहार"
      ],
      "correct_index": 1,
      "category": "social_engineering",
      "explanation": "मасс-Ф़ॉरवर्ड किए गए 'गिवअवे' लिंक अक्सर 'सर्वेक्षण स्कैम' या फ़िशिंग जाल होते हैं।"
    },
    {
      "id": 6,
      "question": "निम्नलिखित में से कोटक बैंक के लिए सबसे सुरक्षित यूआरएल कौन सा है?",
      "options": [
        "http://kotak-support-verify.com/login",
        "https://kotak.net/customer-update",
        "https://www.kotak.com/personal-banking"
      ],
      "correct_index": 2,
      "category": "link_safety",
      "explanation": "हमेशा बैंक का आधिकारिक डोमेन देखें। बैंकिंग के लिए 'सपोर्ट' या 'नेट' जैसे वैकल्पिक एक्सटेंशन से बचें।"
    },
    {
      "id": 7,
      "question": "आपको नेटफ्लिक्स से एक ईमेल मिलता है जिसमें कहा गया है कि आपका भुगतान विफल रहा और 2 घंटे में आपका खाता हटा दिया जाएगा। मुख्य लाल झंडा क्या है?",
      "options": [
        "गंभीर तात्कालिकता और डिलीट होने की धमकी",
        "ईमेल में नेटफ्लिक्स का लोगो है",
        "ईमेल 'प्रिय ग्राहक' के रूप में संबोधित किया गया है"
      ],
      "correct_index": 0,
      "category": "social_engineering",
      "explanation": "कृत्रिम तात्कालिकता फ़िशर्स द्वारा इस्तेमाल की जाने वाली एक पारंपरिक मनोवैज्ञानिक चाल है जो सोच-विचार को रोकने के लिए है।"
    },
    {
      "id": 8,
      "question": "कोई आपको एक आइटम बेचने के लिए 'भुगतान प्राप्त करने' के लिए एक क्यूआर कोड भेजता है। क्या यह स्कैन करना सुरक्षित है?",
      "options": [
        "हाँ, स्कैनिंग भुगतान प्राप्त करने के लिए है",
        "केवल अगर आप एक सत्यापित भुगतान ऐप का उपयोग करते हैं",
        "नहीं, क्यूआर कोड स्कैन करना भुगतान भेजने के लिए है, प्राप्त करने के लिए नहीं"
      ],
      "correct_index": 2,
      "category": "banking",
      "explanation": "क्यूआर कोड भेजने के लिए हैं। अगर कोई आपको प्राप्त करने के लिए एक कोड स्कैन करने के लिए कहता है, तो यह एक घोटाला है।"
    },
    {
      "id": 9,
      "question": "एक संदेश दावा करता है कि आपके पास एक 'लंबित कर रिफंड' है और आपको अपना पैन और बैंक विवरण देने के लिए कहता है। आप कैसे प्रतिक्रिया देंगे?",
      "options": [
        "विवरण भरें ताकि मुझे मेरा रिफंड मिल सके",
        "इसे अनदेखा करें; आयकर विभाग आधिकारिक पोर्टल का उपयोग करता है, एसएमएस नहीं",
        "जांचें कि भेजने वाले का नंबर पेशेवर दिखता है"
      ],
      "correct_index": 1,
      "category": "personal_info",
      "explanation": "सरकारी एजेंसियां एसएमएस के माध्यम से पैन या बैंक विवरण जैसी संवेदनशील जानकारी नहीं मांगती हैं।"
    },
    {
      "id": 10,
      "question": "'विशिंग' का Full Form क्या है?",
      "options": [
        "वॉयस फ़िशिंग (फोन कॉल पर फ़िशिंग)",
        "वीडियो फ़िशिंग",
        "विज़ुअल फ़िशिंग"
      ],
      "correct_index": 0,
      "category": "social_engineering",
      "explanation": "विशिंग फोन कॉल के माध्यम से फ़िशिंग है जो व्यक्तिगत जानकारी चोरी करने के लिए की जाती है।"
    },
    {
      "id": 11,
      "question": "आपको एक लिंक दिखाई देता है: 'https://paypال.com' (एक विशेष 'а' के साथ)। यह हमला क्या कहलाता है?",
      "options": [
        "पात्र हमला",
        "होमोग्राफ हमला",
        "लिंक स्वैपिंग"
      ],
      "correct_index": 1,
      "category": "link_safety",
      "explanation": "होमोग्राफ हमले विभिन्न अल्फाबेट्स के समान दिखने वाले अक्षरों का उपयोग करके डोमेन की नकल करते हैं।"
    },
    {
      "id": 12,
      "question": "एक भर्तीकर्ता आपको एक उच्च-वेतन वाली 'वर्क फ्रॉम होम' नौकरी की पेशकश करता है जिसके लिए 'सुरक्षा जमा' की आवश्यकता होती है। क्या आप भुगतान करते हैं?",
      "options": [
        "हाँ, यह एक अच्छी नौकरी के लिए एक छोटी सी कीमत है",
        "केवल अगर वे पहले एक अनुबंध प्रदान करते हैं",
        "नहीं, वास्तविक कंपनियां नौकरी देने के लिए आपको पैसे नहीं देती"
      ],
      "correct_index": 2,
      "category": "social_engineering",
      "explanation": "नौकरी के घोटाले अक्सर 'जमा' के रूप में पैसे मांगते हैं। असली नियोक्ता आपको भुगतान करते हैं, आप उन्हें नहीं देते।"
    },
    {
      "id": 13,
      "question": "आपके बॉस आपको एक तत्काल ईमेल भेजते हैं जिसमें उन्हें उपहार कार्ड खरीदने और कोड भेजने के लिए कहते हैं। आप क्या करते हैं?",
      "options": [
        "सीधे अपने बॉस से संपर्क करें और अनुरोध की पुष्टि करें",
        "तुरंत उन्हें खरीदें ताकि आप कुशलता दिखा सकें",
        "कंपनी के क्रेडिट कार्ड के लिए पहले पूछें"
      ],
      "correct_index": 0,
      "category": "social_engineering",
      "explanation": "उपहार कार्ड अनुरोध 'बिजनेस ईमेल कम्प्रोमाइज' घोटालों का एक सामान्य रूप है। हमेशा अन्य चैनल के माध्यम से सत्यापित करें।"
    },
    {
      "id": 14,
      "question": "एक ऐप आपके सभी एसएमएस संदेशों को पढ़ने की अनुमति मांगता है। क्या आप अनुमति देते हैं?",
      "options": [
        "हाँ, कई ऐप ओटीपी के लिए इसकी आवश्यकता होती है",
        "नहीं, यह आने वाले बैंक ओटीपी चोरी कर सकता है",
        "केवल अगर यह प्ले स्टोर से है"
      ],
      "correct_index": 1,
      "category": "personal_info",
      "explanation": "दुर्भाग्यपूर्ण ऐप एसएमएस अनुमति का उपयोग बैंक ओटीपी 'सूंघने' और चोरी करने के लिए करते हैं जैसे ही वे आते हैं।"
    },
    {
      "id": 15,
      "question": "यदि आप दुर्भाग्य से एक फ़िशिंग साइट पर अपना पासवर्ड दर्ज करते हैं, तो पहला महत्वपूर्ण कदम क्या है?",
      "options": [
        "पुलिस को बुलाएं",
        "देखें और देखें कि क्या कुछ होता है",
        "तुरंत वास्तविक साइट पर अपना पासवर्ड बदलें"
      ],
      "correct_index": 2,
      "category": "personal_info",
      "explanation": "गति महत्वपूर्ण है। जल्दी से अपना पासवर्ड बदलना हमलावर को बाहर निकाल सकता है।"
    }
  ],
  "mr": [
    {
      "id": 1,
      "question": "तुम्हाला SMS येतो की तुमचा बँक खाते विश्रांत आहे आणि तुम्ही लिंकवर क्लिक करून तुमचे खाते तपासणे आवश्यक आहे. तुम्ही काय कराल?",
      "options": [
        "संदेश विसरून जा आणि थेट बँक ऐप चेक करा",
        "लिंकवर लगेच क्लिक करून ते सुधारा",
        "संदेशाच्या तपशीलांबद्दल विचारण्यासाठी एसएमएसला प्रतिसाद द्या"
      ],
      "correct_index": 0,
      "category": "banking",
      "explanation": "बँका कधीही एसएमएसमधील लिंकद्वारे तुमचे खाते तपासण्यासाठी विनंती करत नाहीत. नेहमी अधिकृत अॅप किंवा वेबसाइट वापरा."
    },
    {
      "id": 2,
      "question": "कोणता लिंक हानीकारक असू शकतो हे ओळखण्याचे चिन्ह काय आहे?",
      "options": [
        "https:// वापरतो",
        "डोमेन नाव थोडेसे चुकीचे आहे (उदा. g00gle.com)",
        "ते खूप लांब आहे"
      ],
      "correct_index": 1,
      "category": "link_safety",
      "explanation": "टाइपोस्क्वाटिंग हा एक सामान्य तरकीब आहे जिथे हल्लेकरी प्रत्यक्ष डोमेनसारखे दिसणारे डोमेन वापरतात परंतु त्यामध्ये सूक्ष्म चुका असतात."
    },
    {
      "id": 3,
      "question": "तुम्हाला एसएमएस मिळतो ज्यामध्ये तुमचा ईमेल आणि फोन नंबर प्रदान केल्यास तुम्हाला $1,000 ची भेट कार्ड मिळेल. हे सुरक्षित आहे का?",
      "options": [
        "होय, कंपन्या नेहमी गिव्हअवे करतात",
        "फक्त तुमचे पूर्ण नाव संदेशामध्ये समाविष्ट केले तर",
        "नाही, जर ते खूप चांगले वाटत असेल तर हे खरे नसेल"
      ],
      "correct_index": 2,
      "category": "personal_info",
      "explanation": "अपेक्षित बक्षिसे हे क्लासिक फिशिंग ल्यूर्स आहेत ज्याचा उद्देश तुमची वैयक्तिक माहिती चोरणे आहे."
    },
    {
      "id": 4,
      "question": "तुमच्या बँकेच्या 'फ्रॉड विभागातील' कोलर तुमच्या खात्याची सुरक्षा सुनिश्चित करण्यासाठी ओटीपी मागतो. तुम्ही द्या का?",
      "options": [
        "नाही, बँका फोनवर ओटीपी मागत नाहीत",
        "होय, ते मला मदत करण्याचा प्रयत्न करत आहेत",
        "फक्त ते तुमचा अकाउंट नंबर आधीपासून माहित असल्यास"
      ],
      "correct_index": 0,
      "category": "banking",
      "explanation": "ओटीपी (वन-टाइम पासवर्ड) फक्त तुमच्या डोळ्यांसाठीच आहे. बँका कधीही फोनवर ते मागत नाहीत."
    },
    {
      "id": 5,
      "question": "तुमचा मित्र तुम्हाला 'फ्री आयफोन गिव्हअवे' साठी व्हाट्सएपवर लिंक पाठवतो ज्यासाठी तुम्हाला ते 10 मित्रांना पुढे पाठवणे आवश्यक आहे. हे काय असू शकते?",
      "options": [
        "व्हायरल मार्केटिंग मोहिम",
        "संपर्क तपशील संग्रहणासाठी फिशिंग स्केम",
        "मोठ्या कॉर्पोरेशनकडून वास्तविक भेट"
      ],
      "correct_index": 1,
      "category": "social_engineering",
      "explanation": "मास-forwarded 'गिव्हअवे' लिंक्स हे अनेकदा 'सर्वेक्षण स्केम' किंवा फिशिंग जाल आहेत."
    },
    {
      "id": 6,
      "question": "यापैकी कोटक बँकेसाठी सुरक्षिततेचा URL कोणता आहे?",
      "options": [
        "http://kotak-support-verify.com/login",
        "https://kotak.net/customer-update",
        "https://www.kotak.com/personal-banking"
      ],
      "correct_index": 2,
      "category": "link_safety",
      "explanation": "नेहमी बँकेचे अधिकृत डोमेन शोधा. बँकिंगसाठी 'सपोर्ट' किंवा .net सारखे पर्यायी एक्सटेंशन टाळा."
    },
    {
      "id": 7,
      "question": "तुम्हाला 'नेटफ्लिक्स' वरुन ईमेल येतो ज्यामध्ये तुमचा पेमेंट अयशस्वी झाला आहे आणि तुमचा अकाउंट 2 तासांत डिलीट केला जाईल. असा मुख्य लाल ध्वज कोणता आहे?",
      "options": [
        "चुकीची तातड्यता आणि डिलीट होण्याचा धोका",
        "ईमेल नेटफ्लिक्स लोगो वापरतो",
        "ईमेल 'प्रिय ग्राहक' या शीर्षकाने संबोधित केला जातो"
      ],
      "correct_index": 0,
      "category": "social_engineering",
      "explanation": "कृत्रिम तातड्यता हा फिशर्सद्वारे वापरलेला एक क्लासिक मानसशास्त्रीय ट्रिक आहे ज्याचा वापर स्पष्ट विचार करण्यापासून रोखण्यासाठी केला जातो."
    },
    {
      "id": 8,
      "question": "कोणी तुम्हाला 'पेमेंट प्राप्त करण्यासाठी' एक QR कोड पाठवतो ज्यासाठी तुम्ही ऑनलाइन वस्तू विक्री करत आहात. तुम्ही ते स्कॅन करणे सुरक्षित आहे का?",
      "options": [
        "होय, स्कॅनिंग ही पेमेंट प्राप्त करण्याची आहे",
        "फक्त तुम्ही वरिफाइड पेमेंट अॅप वापरता",
        "नाही, QR कोड स्कॅन करणे ही पेमेंट करण्याची प्रक्रिया आहे, प्राप्त करण्याची नाही"
      ],
      "correct_index": 2,
      "category": "banking",
      "explanation": "QR कोड हे पेमेंट पाठविण्यासाठी वापरले जातात. जर कोणी तुम्हाला पेमेंट प्राप्त करण्यासाठी कोड स्कॅन करण्यास सांगितले तर ते घोटाळा आहे."
    },
    {
      "id": 9,
      "question": "एक संदेश असा दावा करतो की तुमच्याकडे 'पेंडिंग टॅक्स रिफंड' आहे आणि तुमचा पॅन आणि बँक तपशील मागतो. तुम्ही कसे प्रतिसाद द्याल?",
      "options": [
        "तुमची माहिती भरा जेणेकरून तुम्ही रिफंड प्राप्त करू शकाल",
        "तुम्ही ते विसरून जा; आयटी विभाग अधिकृत पोर्टलचा वापर करतो, एसएमएस नाही",
        "तुम्ही तपासा की संदेशवाहाचा नंबर व्यावसायिक दिसतो का"
      ],
      "correct_index": 1,
      "category": "personal_info",
      "explanation": "सरकारी संस्था कधीही एसएमएसद्वारे संवेदनशील माहिती जसे की पॅन किंवा बँक तपशील विचारत नाहीत."
    },
    {
      "id": 10,
      "question": "विषिंगचे संक्षिप्त रूप काय आहे?",
      "options": [
        "व्हॉइस फिशिंग (फोन कॉलवर फिशिंग)",
        "व्हिडिओ फिशिंग",
        "व्हिज्युअल फिशिंग"
      ],
      "correct_index": 0,
      "category": "social_engineering",
      "explanation": "विषिंग ही फोन कॉलद्वारे फिशिंग आहे ज्याचा वापर लोकांना वैयक्तिक माहिती देण्यासाठी भूलथापने करण्यात आला आहे."
    },
    {
      "id": 11,
      "question": "तुम्ही लिंक पाहता 'https://paypаl.com' (विशेष 'а' सह). ही हमला काय म्हणजे?",
      "options": [
        "चरित्र हल्ला",
        "होमोग्राफ हल्ला",
        "लिंक स्वॅपिंग"
      ],
      "correct_index": 1,
      "category": "link_safety",
      "explanation": "होमोग्राफ हल्ले इतर अल्फाबेट्समधून सारखे दिसणारे अक्षर वापरतात ज्याचा वापर डोमेन चोरण्यासाठी केला जातो."
    },
    {
      "id": 12,
      "question": "एक भरतीकर्ता तुम्हाला 'वर्क फ्रॉम होम' नौकरीची ऑफर देतो ज्यासाठी 'सुरक्षा डिपॉझिट' आवश्यक आहे. तुम्ही पैसे द्या का?",
      "options": [
        "होय, ही चांगल्या नौकरीसाठी एक छोटी किंमत आहे",
        "फक्त ते तुम्हाला करार प्रथम प्रदान केल्यास",
        "नाही, वास्तविक नियोक्ते तुम्हाला नोकरी देण्यासाठी पैसे मागत नाहीत; तुम्ही त्यांना पैसे देत नाही"
      ],
      "correct_index": 2,
      "category": "social_engineering",
      "explanation": "नौकरी घोटाळे अनेकदा नियुक्तीपूर्वी 'डिपॉझिट' मागतात. वास्तविक नियोक्ते तुम्हाला पैसे देतात; तुम्ही त्यांना पैसे देत नाही."
    },
    {
      "id": 13,
      "question": "तुमचा वरिष्ठ तुम्हाला तातड्याने गिफ्ट कार्ड खरेदी करण्यास सांगतो आणि कोड पाठवा. तुम्ही काय कराल?",
      "options": [
        "तुमचा वरिष्ठ थेट संपर्क करण्यासाठी कॉल करा आणि विनंती तपासा",
        "ते त्याबद्दल कार्यवाही करण्यासाठी लगेच खरेदी करा",
        "कंपनी क्रेडिट कार्ड मागून घ्या"
      ],
      "correct_index": 0,
      "category": "social_engineering",
      "explanation": "गिफ्ट कार्ड विनंत्या हा बिझनेस ईमेल कॉम्प्रोमाइझ स्केमचा एक सामान्य प्रकार आहे. नेहमी दुसऱ्या चॅनेलद्वारे ते तपासा."
    },
    {
      "id": 14,
      "question": "कोणती अॅप तुमच्या सर्व एसएमएस संदेश वाचण्यासाठी परवानगी मागते? तुम्ही परवानगी द्या का?",
      "options": [
        "होय, अनेक अॅप ओटीपी साठी ही परवानगी आवश्यक आहे",
        "नाही, ही अॅप बँक ओटीपी चोरू शकते",
        "फक्त ते प्ले स्टोरवरून असल्यास"
      ],
      "correct_index": 1,
      "category": "personal_info",
      "explanation": "दुर्भाग्यशील अॅप्स एसएमएस परवानगी वापरून बँक ओटीपी 'स्निफ' आणि चोरी करू शकतात."
    },
    {
      "id": 15,
      "question": "तुम्ही फिशिंग साइटवर तुमचा पासवर्ड चुकून टाकला तर पहिली महत्त्वपूर्ण काम काय आहे?",
      "options": [
        "पोलीस कॉल करा",
        "थांबा आणि पाहा काही घडते का",
        "तुमचा पासवर्ड ताबडतोब बदला वास्तविक साइटवर"
      ],
      "correct_index": 2,
      "category": "personal_info",
      "explanation": "वेग ही महत्त्वपूर्ण बाब आहे. तुमचा पासवर्ड लवकरात लवकर बदलल्यास हल्लेकरू तुमच्या खात्यापासून दूर राहिल."
    }
  ],
  "bn": [
    {
      "id": 1,
      "question": "আপনি একটি এসএমএস পান যে আপনার ব্যাংক অ্যাকাউন্ট স্থগিত করা হয়েছে এবং আপনাকে একটি লিঙ্কে ক্লিক করতে হবে যাতে এটি নিশ্চিত করা যায়। আপনি কী করবেন?",
      "options": [
        "বার্তাটি উপেক্ষা করুন এবং সরাসরি আপনার ব্যাঙ্কের অ্যাপ চেক করুন",
        "সমস্যাটি সমাধান করতে অবিলম্বে লিঙ্কটিতে ক্লিক করুন",
        "বিবরণের জন্য এসএমএসটির উত্তর দিন"
      ],
      "correct_index": 0,
      "category": "banking",
      "explanation": "ব্যাঙ্কগুলি কখনই একটি এসএমএস-এ একটি লিঙ্কের মাধ্যমে আপনার অ্যাকাউন্ট যাচাই করতে বলবে না। সর্বদা আনুষ্ঠানিক অ্যাপ বা ওয়েবসাইট ব্যবহার করুন।"
    },
    {
      "id": 2,
      "question": "একটি লিঙ্কের ক্ষতিকারক হওয়ার একটি লক্ষণ কী?",
      "options": [
        "এটি 'https://' ব্যবহার করে",
        "ডোমেইন নামটি সামান্য ভুল (যেমন, g00gle.com)",
        "এটি খুব লম্বা"
      ],
      "correct_index": 1,
      "category": "link_safety",
      "explanation": "টাইপস্কয়াটিং হল একটি সাধারণ কৌশল যেখানে আক্রমণকারীরা প্রকৃত মতো দেখতে ডোমেইন ব্যবহার করে কিন্তু সূক্ষ্ম ত্রুটি থাকে।"
    },
    {
      "id": 3,
      "question": "একটি এসএমএস আপনাকে $1000 উপহার কার্ড অফার করে যদি আপনি আপনার ইমেইল এবং ফোন নম্বর প্রদান করেন। এটা নিরাপদ?",
      "options": [
        "হ্যাঁ, কোম্পানিগুলি প্রায়শই গিভঅ্যাওয়ে করে",
        "শুধুমাত্র যদি বার্তাটিতে আপনার পূর্ণ নাম থাকে",
        "না, যদি এটি খুব ভাল মনে হয়, তবে এটি সম্ভবত তা নয়"
      ],
      "correct_index": 2,
      "category": "personal_info",
      "explanation": "অপ্রত্যাশিত পুরস্কারগুলি আপনার ব্যক্তিগত তথ্য চুরি করার জন্য ডিজাইন করা ক্লাসিক ফিশিং লুজ।"
    },
    {
      "id": 4,
      "question": "একজন কলার যিনি নিজেকে আপনার ব্যাঙ্কের 'ফ্রড বিভাগ' থেকে দাবি করেন তিনি আপনার অ্যাকাউন্ট নিরাপদ করার জন্য একটি ওটিপি জিজ্ঞাসা করেন। আপনি কি দেবেন?",
      "options": [
        "না, ব্যাঙ্কগুলি কখনও ফোন কলের মাধ্যমে ওটিপিগুলি জিজ্ঞাসা করে না",
        "হ্যাঁ, তারা আমার সাহায্য করার চেষ্টা করছে",
        "শুধুমাত্র যদি তারা ইতিমধ্যেই আপনার অ্যাকাউন্ট নম্বর জানে"
      ],
      "correct_index": 0,
      "category": "banking",
      "explanation": "একটি ওটিপি (ওন-টাইম পাসওয়ার্ড) শুধুমাত্র আপনার চোখের জন্য। ব্যাঙ্কগুলি কখনই কলের মাধ্যমে এটি জিজ্ঞাসা করে না।"
    },
    {
      "id": 5,
      "question": "একজন বন্ধু আপনাকে হোয়াটসঅ্যাপের মাধ্যমে 'ফ্রি আইফোন গিভঅ্যাওয়ে' এর জন্য একটি লিঙ্ক পাঠায় যার জন্য 10 জন বন্ধুকে এগিয়ে পাঠাতে হবে। এটি সম্ভবত কী?",
      "options": [
        "একটি ভাইরাল বিপণন প্রচার",
        "আপনার যোগাযোগের বিবরণ সংগ্রহ করতে একটি ফিশিং স্ক্যাম",
        "একটি বড় কর্পোরেশনের পক্ষ থেকে একটি প্রকৃত উপহার"
      ],
      "correct_index": 1,
      "category": "social_engineering",
      "explanation": "বিশাল পরিমাণে ফরোয়ার্ড করা 'গিভঅ্যাওয়ে' লিঙ্কগুলি প্রায়শই 'সার্ভে স্ক্যাম' বা ফিশিং ফাঁদ।"
    },
    {
      "id": 6,
      "question": "নিম্নলিখিত ইউআরএলগুলির মধ্যে কোটাক ব্যাঙ্কের জন্য কোনটি সবচেয়ে নিরাপদ ক্লিক করা হবে?",
      "options": [
        "http://kotak-support-verify.com/login",
        "https://kotak.net/customer-update",
        "https://www.kotak.com/personal-banking"
      ],
      "correct_index": 2,
      "category": "link_safety",
      "explanation": "সর্বদা ব্যাঙ্কের আনুষ্ঠানিক ডোমেন খুঁজুন। ব্যাঙ্কিংয়ের জন্য '.net' এর মতো বিকল্প এক্সটেনশন বা 'সাপোর্ট' এড়িয়ে যান।"
    },
    {
      "id": 7,
      "question": "আপনি 'নেটফ্লিক্স' থেকে একটি ইমেইল পান যা বলে যে আপনার অর্থপ্রদান ব্যর্থ হয়েছে এবং 2 ঘন্টার মধ্যে আপনার অ্যাকাউন্ট মুছে ফেলা হবে। প্রধান লাল পতাকা কী?",
      "options": [
        "চরম জরুরি এবং মুছে ফেলার হুমকি",
        "ইমেইলটি নেটফ্লিক্স লোগো ব্যবহার করে",
        "ইমেইলটি 'প্রিয় গ্রাহক' হিসাবে ঠিকানা করা হয়"
      ],
      "correct_index": 0,
      "category": "social_engineering",
      "explanation": "কৃত্রিম জরুরি হল ফিশারদের দ্বারা ব্যবহৃত একটি শাস্ত্রীয় মনস্তাত্ত্বিক কৌশল স্পষ্ট চিন্তাভাবনা প্রতিরোধ করতে।"
    },
    {
      "id": 8,
      "question": "কেউ আপনাকে অনলাইনে বিক্রি করা একটি আইটেমের জন্য 'অর্থপ্রদান গ্রহণ' করতে একটি কিউআর কোড পাঠায়। এটি নিরাপদ কিনা স্ক্যান করা হচ্ছে?",
      "options": [
        "হ্যাঁ, স্ক্যানিং হল অর্থ গ্রহণের জন্য",
        "শুধুমাত্র যদি আপনি একটি ভেরিফাইড পেমেন্ট অ্যাপ ব্যবহার করেন",
        "না, কিউআর কোড স্ক্যান করা অর্থ প্রেরণের জন্য, গ্রহণ নয়"
      ],
      "correct_index": 2,
      "category": "banking",
      "explanation": "কিউআর কোডগুলি অর্থ প্রেরণ করতে ব্যবহৃত হয়। যদি কেউ আপনাকে অর্থ গ্রহণের জন্য একটি কোড স্ক্যান করতে বলে, তবে এটি একটি স্ক্যাম।"
    }
  ],
  "pa": [
    {
      "id": 1,
      "question": "ਸੁਜ ਨ੍ ਸਾ ਕੇ ਪਿਜੋ ਦਾ ਸਿ ਮ ਸ੍ ਪਾ ਸਿ ਕ੍ ਸੀ ਪਿ ਜ ੀਪਾ ਸਿ ਪਿ ਜ ਸਿ ਪਾ ਸਿਜ ਸਿ ਦਾ ਸਮ ਸਜ ਪਿ ਜ ਸਿ ਦਾ ਕੋ ਸਿ ਪਿ ਜ ਸਿ ਨ੍ ਸਿ ਮ ਸੀ ਪਿ ਜ ਸਿ ੀਪਾ ਸਿ ਪਿ ਜ੍?",
      "options": [
        "ਨ੍ ਸਿ ੀਪਾ ਸਿ ਪਿ ਜ ਸਿ ਦਾ ਕੋ ਸਿ ਪਿ ਜ ਨ੍ ਸੀ ਪਿ ਜ ਸਿ ੀਪਾ ਸਿ ਪਿ ਜ",
        "ਪਿ ਜ ਸਿ ਨ੍ ਸਿ ਮ ਸੀ ਪਿ ਜ ਸਿ ਦਾ ੀਪਾ ਸਿ ਪਿ ਜ ਸਿ ਨ੍ ਸਿ ਮ ਸੀ ਪਿ ਜ",
        "ਸਿ ਨ੍ ਸੀ ਪਿ ਜ ਸਿ ੀਪਾ ਸਿ ਪਿ ਜ ਦਾ ਕੋ ਸਿ ਪਿ ਜ ਸਿ ੀਪਾ ਸਿ ਪਿ ਜ੍"
      ],
      "correct_index": 0,
      "category": "banking",
      "explanation": "ਮ ਜੋ ਦਾ ਨ੍ ਸਿ ਮ ਸੀ ਪਿ ਜ ਸਿ ਦਾ ਕੋ ਪਿ ਜ ਸਿ ੀਪਾ ਸਿ ਪਿ ਜ ਨ੍ ਸਿ ਮ ਸੀ ਦਾ ਸਮ ਜ ਨ੍ ਸਿ ਮ ਸੀ ਪਿ ਜ ਸਿ ੀਪਾ ਸਿ ਪਿ ਜ੍ ਸਿ ਦਾ ਕੋ ਪਿ ਜ ਸਿ ੀਪਾ ਸਿ ਪਿ ਜ੍"
    },
    {
      "id": 2,
      "question": "ਸਾ ਪਿ ਜ ਪਾ ਸੀ ਦਾ ਨ੍ ਦਾ ਕੋ ਪਿ ਜ ਸਿ ਮ ਪਾ ਸਿ ਦਾ ਸਮ ਸਜ ਪਿ ਜ ਸਿ ਦਾ ਕੋ ਸਿ ਪਿ ਜ ਨ੍?",
      "options": [
        "ਸਾ ਪਾ ਸੀ ਕ੍ ਨ੍ ਸਿ ਮ ਦਾ ਸਮ ਨ੍ ਮ ਪਿ ਜ ੀਪਾ ਸਿ ਪਿ ਜ ਦਾ ਸਮ ਪਿ ਜ ਸਿ ਦਾ ਕੋ ਸਿ ਪਿ ਜ",
        "ਸੀ ਪਿ ਜ ਨ੍ ਸਿ ਮ ਸੀ ਪਿ ਜ ਮ ਪਿ ਜ ਸਿ ਦਾ ਕੋ ਪਿ ਜ ਸਿ ੀਪਾ ਸਿ ਪਿ ਜ ਨ੍ ਸਿ ਮ ਸੀ ਪਿ ਜ",
        "ਸਾ ਪਾ ਸੀ ਸਿ ਦਾ ਕੋ ਪਿ ਜ ਸਿ ੀਪਾ ਸਿ ਪਿ ਜ ਨ੍ ਸਿ ਮ ਪਿ ਜ ਸਿ ਦਾ ਕੋ ਸਿ ਪਿ ਜ"
      ],
      "correct_index": 1,
      "category": "link_safety",
      "explanation": "ਸਾ ਪਾ ਸੀ ਸਿ ਮ ਦਾ ਕੋ ਪਿ ਜ ਮ ਪਿ ਜ ੀਪਾ ਸਿ ਪਿ ਜ ਪਾ ਸਿ ਮ ਸੀ ਦਾ ਨ੍ ਸਿ ਮ ਪਿ ਜ ਸਿ ਮ ਨ੍ ਮ ਸੀ ਦਾ ਸਮ ਸਜ ਪਿ ਜ ਪਾ ਸਿ ਦਾ ਸਮ ਪਿ ਜ ਸਿ ੀਪਾ ਸਿ ਪਿ ਜ ਸਿ ਮ ਦਾ ਕੋ ਸਿ ੀਪਾ ਸਿ ਪਿ ਜ ਦਾ ਸਮ ਪਿ ਜ ਸਿ ਮ ਪਾ ਸੀ ਪਿ ਜ ਸਿ ੀਪਾ ਸਿ ਪਿ ਜ"
    }
  ],
  "ta": [
    {
      "id": 1,
      "question": "உங்கள் வங்கி கணக்கு நிறுத்தப்பட்டுள்ளது என்று ஒரு எஸ்எம்எஸ் சொல்கிறது, மேலும் அதை உறுதிப்படுத்த ஒரு இணைப்பைக் கிளிக் செய்ய வேண்டும். நீங்கள் என்ன செய்கிறீர்கள்?",
      "options": [
        "செய்தியை புறக்கணித்து நேரடியாக உங்கள் வங்கி பயன்பாட்டைப் பார்க்கவும்",
        "அதைத் தீர்க்க இணைப்பை உடனடியாக கிளிக் செய்யுங்கள்",
        "விவரங்களைக் கேட்டு எஸ்எம்எஸுக்கு பதில் அனுப்புங்கள்"
      ],
      "correct_index": 0,
      "category": "banking",
      "explanation": "வங்கிகள் ஒரு எஸ்எம்எஸ்ல் மூலம் உங்கள் கணக்கை உறுதிப்படுத்த அனுமதிக்கும். எப்போதும் அதிகாரப்பூர்வ பயன்பாட்டையோ அல்லது தளத்தையோ பயன்படுத்தவும்."
    },
    {
      "id": 2,
      "question": "ஒரு இணைப்பு தீங்கு விளைவிக்கக்கூடியதா என்பதற்கான அறிகுறி என்ன?",
      "options": [
        "அது 'https://' ஐப் பயன்படுத்துகிறது",
        "டொமைன் பெயர் சிறிது தவறாக உச்சரிக்கப்பட்டுள்ளது (எ.கா, g00gle.com)",
        "அது மிகவும் நீண்டது"
      ],
      "correct_index": 1,
      "category": "link_safety",
      "explanation": "டைப்போஸ்குவாட்டிங் என்பது ஒரு பொதுவான சாதனம், இதில் தாக்குநர்கள் உண்மையானவற்றைப் போலவே தோற்றமளிக்கும் ஆனால் சிறிய பிழைகளுடன் கூடிய டொமைன்களைப் பயன்படுத்துகிறார்கள்."
    },
    {
      "id": 3,
      "question": "உங்கள் மின்னஞ்சல் மற்றும் தொலைபேசி எண்ணை வழங்குவதன் மூலம் உங்களுக்கு $1,000 பரிசு அட்டையை வழங்கும் ஒரு எஸ்எம்எஸ் உள்ளது. இது பாதுகாப்பானதா?",
      "options": [
        "ஆம், நிறுவனங்கள் அனைத்து நேரங்களிலும் பரிசுகளை வழங்குகின்றன",
        "சரியானது, செய்தியில் உங்கள் முழு பெயர் இருந்தால் மட்டும்",
        "இல்லை, அது நன்றாக இருக்கும் அளவுக்கு நன்றாக ஒலிக்கும் போது அது பொதுவாக உண்மையல்ல"
      ],
      "correct_index": 2,
      "category": "personal_info",
      "explanation": "எதிர்பாராத பரிசுகள் உங்கள் தனிப்பட்ட தகவல்களைத் திருட வடிவமைக்கப்பட்ட புகழ்பெற்ற மீன்பிடி ஈர்க்கல்கள்."
    },
    {
      "id": 4,
      "question": "உங்கள் வங்கியின் 'மோசடி துறையின்' பேரில் ஒரு அழைப்பாளர் உங்கள் கணக்கை பாதுகாப்பாக வைக்க ஒரு ஒரு முறை குறியீட்டை (OTP) கேட்கிறார். நீங்கள் அதை கொடுக்கிறீர்களா?",
      "options": [
        "இல்லை, வங்கிகள் ஒரு அழைப்பின் மூலம் OTP ஐ கேட்காது",
        "ஆம், அவர்கள் என்னை உதவியாக இருக்கிறார்கள்",
        "ஒரு OTP ஐக் கேட்டால் மட்டும், அவர்கள் இதற்கு முன் உங்கள் கணக்கு எண்ணை அறிந்திருந்தால்"
      ],
      "correct_index": 0,
      "category": "banking",
      "explanation": "ஒரு ஒரு முறை குறியீடு (OTP) உங்கள் கண்களுக்காக மட்டுமே. வங்கிகள் ஒரு அழைப்பின் மூலம் அதைக் கேட்காது."
    },
    {
      "id": 5,
      "question": "உங்களுக்கு WhatsApp மூலம் 'இலவச iPhone பரிசு' இன் இணைப்பை ஒரு நண்பர் அனுப்புகிறார், அது 10 நண்பர்களுக்கு அனுப்ப வேண்டும். இது பொதுவாக என்ன என்று அழைக்கப்படுகிறது?",
      "options": [
        "வைரல் மக்கிங் பிரச்சாரம்",
        "தொடர்பு விவரங்களை சேகரிக்க ஒரு மீன்பிடி மோசடி",
        "ஒரு பெரிய கார்ப்பரேஷனில் இருந்து ஒரு உண்மையான பரிசு"
      ],
      "correct_index": 1,
      "category": "social_engineering",
      "explanation": "பரவலாக முன்னோக்கிச் செலுத்தப்படும் 'பரிசு' இணைப்புகள் பெரும்பாலும் 'ஆய்வு மோசடிகள்' அல்லது மீன்பிடி பொறிகளாகும்."
    }
  ],
  "te": [
    {
      "id": 1,
      "question": "మీ బ్యాంక్ ఖాతా నిలిపివేయబడిందని, దాన్ని నిర్ధారించడానికి ఒక లింక్‌ను క్లిక్ చేయాల్సి ఉంటుందని ఒక ఎస్‌ఎంఎస్ వస్తుంది. మీరు ఏమి చేస్తారు?",
      "options": [
        "సందేశాన్ని విస్మరించి నేరుగా మీ బ్యాంక్ యాప్‌ను తనిఖీ చేయండి",
        "దాన్ని పరిష్కరించడానికి తక్షణమే లింక్‌ను క్లిక్ చేయండి",
        "వివరాలను అడగడానికి ఎస్‌ఎంఎస్‌కు సమాధానం ఇవ్వండి"
      ],
      "correct_index": 0,
      "explanation": "బ్యాంకులు ఎప్పటికీ మీ ఖాతాను ఎస్‌ఎంఎస్‌లోని లింక్ ద్వారా ధృవీకరించమని అడగవు. ఎల్లప్పుడూ అధికారిక యాప్ లేదా వెబ్‌సైట్‌ని ఉపయోగించండి.",
      "category": "banking"
    },
    {
      "id": 2,
      "question": "ఒక లింక్ హానికరమైనది అని సూచించే గుర్తు ఏమిటి?",
      "options": [
        "ఇది 'https://'ని ఉపయోగిస్తుంది",
        "డొమైన్ పేరు కొంచెం తప్పుగా ఉంది (ఉదా, g00gle.com)",
        "ఇది చాలా పొడవుగా ఉంది"
      ],
      "correct_index": 1,
      "explanation": "టైపోస్క్వాటింగ్ అనేది దాడి చేసేవారు నిజమైన వాటితో సున్నితమైన లోపాలు ఉన్న డొమైన్‌లను ఉపయోగించే ఒక సాధారణ వ్యూహం.",
      "category": "link_safety"
    },
    {
      "id": 3,
      "question": "మీ ఇమెయిల్ మరియు ఫోన్ సంఖ్యను అందించమని మీకు $1,000 బహుమతి కార్డ్‌ను అందించే ఒక ఎస్‌ఎంఎస్ వచ్చింది. ఇది భద్రమేనా?",
      "options": [
        "కంపెనీలు అన్నిచోట్లా గివ్‌వేలను నిర్వహిస్తాయి",
        "సందేశం మీ పూర్తి పేరును కలిగి ఉంటే మాత్రమే",
        "లేదు, ఇది చాలా మంచిగా అనిపిస్తే, ఇది నిజం కాకపోవచ్చు"
      ],
      "correct_index": 2,
      "explanation": "అనుకోని బహుమతులు మీ వ్యక్తిగత సమాచారాన్ని దొంగిలించడానికి ఉపయోగించే క్లాసిక్ ఫిషింగ్ ల్యూర్‌లు.",
      "category": "personal_info"
    },
    {
      "id": 4,
      "question": "మీ బ్యాంక్ యొక్క 'మోసం విభాగం' నుండి ఒక కాలర్ మీ ఖాతాను భద్రపరిచేందుకు ఒక ఓటిపిని అడుగుతారు. మీరు దాన్ని ఇస్తారా?",
      "options": [
        "లేదు, బ్యాంకులు ఎప్పుడూ ఫోన్‌లో ఓటిపిలను అడగవు",
        "అవును, వారు నాకు సహాయం చేయడానికి ప్రయత్నిస్తున్నారు",
        "వారు ఇప్పటికే మా ఖాతా సంఖ్యను తెలుసుకుంటే మాత్రమే"
      ],
      "correct_index": 0,
      "explanation": "ఒక ఓటిపి (వన్-టైమ్ పాస్‌వోర్డ్) మీ కళ్ళకోసం మాత్రమే. బ్యాంకులు ఎప్పుడూ పిల్లో ఓటిపిని అడగవు.",
      "category": "banking"
    },
    {
      "id": 5,
      "question": "మీకు వాట్సాప్ ద్వారా 'ఉచిత iPhone బహుమతి' కోసం 10 మంది స్నేహితులకు ముందుకు పంపమని ఒక లింక్ వస్తుంది. ఇది ఏమిటి?",
      "options": [
        "వైరల్ మార్కెటింగ్ ప్రచారం",
        "సంపర్క వివరాలను సేకరించడానికి ఫిషింగ్ మోసం",
        "పెద్ద సంస్థ నుండి నిజమైన బహుమతి"
      ],
      "correct_index": 1,
      "explanation": "సర్వే మోసాలు లేదా ఫిషింగ్ ఫందాలుగా ఉండే అవకాశం ఉన్న డబ్బు ముందుకు పంపబడిన 'బహుమతి' లింక్‌లు.",
      "category": "social_engineering"
    },
    {
      "id": 6,
      "question": "కోటక్ బ్యాంక్ కోసం ఈ యూర్ల్‌లలో ఏది క్లిక్ చేయడానికి భద్రమైనది?",
      "options": [
        "http://kotak-support-verify.com/login",
        "https://kotak.net/customer-update",
        "https://www.kotak.com/personal-banking"
      ],
      "correct_index": 2,
      "explanation": "బ్యాంక్ యొక్క అధికారిక డొమైన్ కోసం ఎల్లప్పుడూ చూస్తూ ఉండండి. బ్యాంకింగ్ కోసం '.net' వంటి వేర్వేరు ఎక్స్‌టెన్షన్‌లను నివారించండి.",
      "category": "link_safety"
    }
  ],
  "ml": [
    {
      "id": 1,
      "question": "നിങ്ങളുടെ ബാങ്ക് അക്കൗന്റ് നിർത്തിവച്ചിരിക്കുന്നതായി ഒരു എസ്എംഎസ് വരുന്നു, അത് സ്ഥിരീകരിക്കാൻ ഒരു ലിങ്ക് ക്ലിക്ക് ചെയ്യണമെന്ന് പറയുന്നു. നിങ്ങൾ എന്ത് ചെയ്യും?",
      "options": [
        "സന്ദേശത്തെ അവഗണിക്കുകയും നേരിട്ട് ബാങ്ക് ആപ്പ് ഉപയോഗിച്ച് പരിശോധിക്കുകയും ചെയ്യുക",
        "അത് ശരിയാക്കാൻ ഉടൻ തന്നെ ലിങ്ക് ക്ലിക്ക് ചെയ്യുക",
        "വിശദാംശങ്ങൾ ആരായാൻ എസ്എംഎസ് മറുപടി അയയ്ക്കുക"
      ],
      "correct_index": 0,
      "explanation": "ബാങ്കുകൾ എപ്പോഴും ഒരു എസ്എംഎസിലെ ലിങ്ക് വഴി നിങ്ങളുടെ അക്കൗന്റ് സ്ഥിരീകരിക്കാൻ ആവശ്യപ്പെടില്ല. എല്ലായ്പ്പോഴും ഔദ്യോഗിക ആപ്പ് അല്ലെങ്കിൽ വെബ്സൈറ്റ് ഉപയോഗിക്കുക.",
      "category": "banking"
    },
    {
      "id": 2,
      "question": "ഒരു ലിങ്ക് ദുരുദ്ദേശമുള്ളതായിരിക്കാനുള്ള ഒരു അടയാളം എന്താണ്?",
      "options": [
        "അത് 'https://' ഉപയോഗിക്കുന്നു",
        "ഡൊമെയ്ൻ നാമം ചെറിയതായി തട്ടിക്കൂടിയിരിക്കുന്നു (ഉദാ. g00gle.com)",
        "അത് വളരെ നീണ്ടതാണ്"
      ],
      "correct_index": 1,
      "explanation": "ടൈപ്‌സ്‌ക്വാറ്റിംഗ് എന്നത് ആക്രമണകാരികൾ യഥാർത്ഥത്തിന് സമാനമായ പക്ഷേ ചെറിയ പൊരുത്തക്കേടുകളുള്ള ഡൊമെയ്‌നുകൾ ഉപയോഗിക്കുന്ന ഒരു സാധാരണ തന്ത്രമാണ്.",
      "category": "link_safety"
    },
    {
      "id": 3,
      "question": "നിങ്ങൾക്ക് നിങ്ങളുടെ ഇമെയിൽ വിലാസവും ഫോൺ നമ്പരും നൽകിയാൽ $1,000 സമ്മാന കാർഡ് നൽകാമെന്ന് ഒരു എസ്എംഎസ് വാഗ്ദാനം ചെയ്യുന്നു. ഇത് സുരക്ഷിതമാണോ?",
      "options": [
        "ഇത് സാധാരണമാണ്, കമ്പനികൾ ഇടയ്ക്കിടെ സമ്മാനങ്ങൾ നൽകുന്നു",
        "സന്ദേശത്തിൽ നിങ്ങളുടെ മുഴുവൻ പേര് ഉൾപ്പെടുത്തിയാൽ മാത്രം",
        "ഇല്ല, അത് വളരെ നല്ലതായതിനാൽ അത് യഥാർത്ഥമല്ല"
      ],
      "correct_index": 2,
      "explanation": "പൊതുവെ അറിയപ്പെടുന്ന വിജയങ്ങൾ ഫിഷിംഗ് പാമ്പായി വരുന്ന ഒരു പ്രചോദനമാണ്, അവ നിങ്ങളുടെ വ്യക്തിഗത വിവരങ്ങൾ മോഷ്ടിക്കാൻ ഉദ്ദേശിച്ചുള്ളതാണ്.",
      "category": "personal_info"
    },
    {
      "id": 4,
      "question": "നിങ്ങളുടെ ബാങ്കിന്റെ 'ഫ്രൌഡ് വിഭാഗത്തിൽ നിന്ന്' എന്ന് അവകാശപ്പെടുന്ന ഒരു കോളർ നിങ്ങളുടെ അക്കൗന്റ് സുരക്ഷിതമാക്കാൻ ഒടിപി ആവശ്യപ്പെടുന്നു. നിങ്ങൾ അത് നൽകുമോ?",
      "options": [
        "ഇല്ല, ബാങ്കുകൾ ഫോൺ വഴി ഒടിപി അഭ്യർത്ഥിക്കില്ല",
        "ഇയാലോ, അവർ എന്നെ സഹായിക്കാൻ ശ്രമിക്കുന്നു",
        "അവർ ഇതിനകം നിങ്ങളുടെ അക്കൗന്റ് നമ്പർ അറിയുകയാണെങ്കിൽ മാത്രം"
      ],
      "correct_index": 0,
      "explanation": "ഒരു ഒറ്റ-സമയ പാസ്വർഡ് (ഒടിപി) നിങ്ങളുടെ കണ്ണുകൾക്ക് മാത്രമാണ്. ബാങ്കുകൾ ഒരു വിളിക്കിടയിൽ അത് ആവശ്യപ്പെടില്ല.",
      "category": "banking"
    },
    {
      "id": 5,
      "question": "നിങ്ങളുടെ ഒരു 'ഫ്രീ ഐഫോൺ ഗിവാവേ' എന്ന ലിങ്ക് നിങ്ങളുടെ ഒരു സുഹൃത്ത് വാട്സാപ്പിലൂടെ അയച്ചു, അത് 10 സുഹൃത്തുക്കളുടെ അടുത്തേക്ക് അയക്കണം. ഇത് ഏതാണ്?",
      "options": [
        "ഒരു വൈറൽ മാർക്കറ്റിംഗ് കാമ്പെയ്‌ൻ",
        "അഴിമതിക്കാരുടെ സമ്പർക്കം ശേഖരിക്കാൻ ഒരു ഫിഷിംഗ് തന്ത്രം",
        "ഒരു വലിയ കോർപ്പറേഷനിൽ നിന്ന് യഥാർത്ഥ സമ്മാനം"
      ],
      "correct_index": 1,
      "explanation": "പുനഃക്രമീകരണ ലിങ്കുകൾ 'സർവേ അഴിമതികൾ' അല്ലെങ്കിൽ ഫിഷിംഗ് കെണികളായിരിക്കാം.",
      "category": "social_engineering"
    },
    {
      "id": 6,
      "question": "കോടക് ബാങ്കിനായി ഏത് യുആർഎൽ ക്ലിക്ക് ചെയ്യാൻ ഏറ്റവും സുരക്ഷിതമാണ്?",
      "options": [
        "http://kotak-support-verify.com/login",
        "https://kotak.net/customer-update",
        "https://www.kotak.com/personal-banking"
      ],
      "correct_index": 2,
      "explanation": "എല്ലായ്പ്പോഴും ബാങ്കിന്റെ ഔദ്യോഗിക ഡൊമെൻ പരിശോധിക്കുക. ബാങ്കിംഗിനായി '.net' പോലുള്ള വ്യത്യസ്ത എക്സ്റ്റൻഷനുകൾ ഒഴിവാക്കുക.",
      "category": "link_safety"
    }
  ],
  "gu": [
    {
      "id": 1,
      "question": "તમને SMS આવે છે કે તમારો બેંક એકાઉન્ટ નિલંબિત છે અને તમારે તેને પુષ્ટિ કરવા માટે લિંક પર ક્લિક કરવું જરૂરી છે. તમે શું કરો છો?",
      "options": [
        "સંદેશ નકારીને સીધા બેંકની એપ્લિકેશન ચેક કરો",
        "તરત જ લિંક પર ક્લિક કરીને તેને ઠીક કરો",
        "વધુ વિગતો જાણવા માટે SMSનો જવાબ આપો"
      ],
      "correct_index": 0,
      "category": "banking",
      "explanation": "બેંકો કદી પણ SMSમાં લિંક દ્વારા તમારા એકાઉન્ટને પુષ્ટિ કરવા કહેશે નહીં. હંમેશા સત્તાવાર એપ્લિકેશન અથવા વેબસાઇટ વાપરો."
    },
    {
      "id": 2,
      "question": "લિંક હાનિકારક હોઈ શકે તેનું એક ચિહ્ન શું છે?",
      "options": [
        "તે 'https://' નો ઉપયોગ કરે છે",
        "ડોમેનનું નામ થોડું ખોટું છે (ઉદાહરણ તરીકે, g00gle.com)",
        "તે ખૂબ જ લાંબો છે"
      ],
      "correct_index": 1,
      "category": "link_safety",
      "explanation": "ટાઇપોસ્ક્વોટિંગ એ એક સામાન્ય રમત છે જ્યાં હુમલાકારો વાસ્તવિક ડોમેન સમાન લાગતા પરંતુ નાની ભૂલો સાથેના ડોમેન વાપરે છે."
    },
    {
      "id": 3,
      "question": "SMS તમને $1000નો ભેટ કાર્ડ ઓફર કરે છે જો તમે તમારું ઇમેઇલ અને ફોન નંબર આપો. કે આ સલામત છે?",
      "options": [
        "હા, કંપનીઓ દરેક સમયે આપણી પાસેથી ગામ લે છે",
        "ફક્ત જો સંદેશમાં તમારું પૂરું નામ સમાવિષ્ટ હોય",
        "ના, જો તે ખૂબ સારું લાગે તો તે શક્યતઃ નથી"
      ],
      "correct_index": 2,
      "category": "personal_info",
      "explanation": "અનપેક્ષિત ઈનામો તમારી વ્યક્તિગત માહિતી ચોરી કરવા માટેના ક્લાસિક ફિશિંગ લ્યુર્સ છે."
    },
    {
      "id": 4,
      "question": "એક કૉલર જે તમારી બેંકના 'ફ્રોડ વિભાગ'નો દાવો કરે છે, તે તમારા એકાઉન્ટને સુરક્ષિત કરવા માટે OTP માંગે છે. શું તમે તેને આપો છો?",
      "options": [
        "ના, બેંકો ફોન પર OTP માંગતી નથી",
        "હા, તેઓ મને મદદ કરવાનો પ્રયાસ કરી રહ્યા છે",
        "ફક્ત જો તેઓ પહેલેથી જ તમારા એકાઉન્ટ નંબર જાણતા હોય"
      ],
      "correct_index": 0,
      "category": "banking",
      "explanation": "OTP (વન-ટાઇમ પાસવર્ડ) તમારી આંખો માટે જ છે. બેંકો કદી પણ કૉલ પર OTP માંગશે નહીં."
    },
    {
      "id": 5,
      "question": "તમારા મિત્રએ WhatsApp પર 'ફ્રી આઇફોન ગિવઅવે' માટે લિંક મોકલી છે જે 10 મિત્રોને આગળ મોકલવાની જરૂર છે. આ શું સંભવિત છે?",
      "options": [
        "વાઇરલ માર્કેટિંગ પ્રચાર",
        "સંપર્ક વિગતો એકત્રિત કરવા માટે ફિશિંગ સ્કેમ",
        "મોટી કોર્પોરેશનની વાસ્તવિક ભેટ"
      ],
      "correct_index": 1,
      "category": "social_engineering",
      "explanation": "સર્વે આગળ મોકલવામાં આવતી 'ગિવઅવે' લિંકો 'સર્વે સ્કેમ્સ' અથવા ફિશિંગ જાલની જાળ હોઈ શકે છે."
    },
    {
      "id": 6,
      "question": "કોટક બેંક માટે કયો યુઆરએલ સૌથી સુરક્ષિત છે?",
      "options": [
        "http://kotak-support-verify.com/login",
        "https://kotak.net/customer-update",
        "https://www.kotak.com/personal-banking"
      ],
      "correct_index": 2,
      "category": "link_safety",
      "explanation": "હંમેશા બેંકનું સત્તાવાર ડોમેન શોધો. 'સપોર્ટ' અથવા '.net' જેવા બેંકિંગ માટે વિકલ્પ એક્સટેન્શનનો ઉપયોગ ટાળો."
    },
    {
      "id": 7,
      "question": "તમને 'નેટફ્લિક્સ' પાસેથી એક ઈમેઇલ મળે છે જેમાં કહેવામાં આવે છે કે તમારી ચૂકવણી નિષ્ફળ ગઈ છે અને તમારું એકાઉન્ટ 2 કલાકમાં ડિલેટ થઈ જશે. મુખ્ય ચેતવણી કાં તો કે છે?",
      "options": [
        "તીવ્રતા અને ડિલેશનની ધમકી",
        "ઈમેઇલ નેટફ્લિક્સનો લોગો ઉપયોગ કરે છે",
        "ઈમેઇલ 'પ્રિય ગ્રાહક' તરીકે સંબોધન કરે છે"
      ],
      "correct_index": 0,
      "category": "social_engineering",
      "explanation": "કૃત્રિમ તીવ્રતા એ ફિશરો દ્વારા ઉપયોગમાં લેવામાં આવતી ક્લાસિક માનસિક ટ્રિક છે જે સ્પષ્ટ વિચારણાને અટકાવવા માટે છે."
    }
  ],
  "ur": [
    {
      "id": 1,
      "question": "آپ کو ایک ایس ایم ایس آتا ہے جو کہتا ہے کہ آپ کا بینک اکاؤنٹ معطل کر دیا گیا ہے اور آپ کو اسے وریفائی کرنے کے لیے ایک لنک پر کلک کرنا ہوگا۔ آپ کیا کریں گے?",
      "options": [
        "میسج کو نظرانداز کریں اور براہ راست بینک ایپ چیک کریں",
        "فوری طور پر لنک پر کلک کریں تاکہ اسے ٹھیک کیا جا سکے",
        "ایس ایم ایس کا جواب دیں اور تفصیلات مانگےں"
      ],
      "correct_index": 0,
      "category": "banking",
      "explanation": "بینک کبھی بھی آپ سے ایس ایم ایس میں لنک کے ذریعے اپنے اکاؤنٹ کی وریفیکیشن کے لیے نہیں کہیں گے۔ ہمیشہ سرکاری ایپ یا ویب سائٹ کا استعمال کریں۔"
    },
    {
      "id": 2,
      "question": "کسی لنک کے خطرناک ہونے کی علامت کیا ہے?",
      "options": [
        "یہ 'https://' کا استعمال کرتا ہے",
        "ڈومین کا نام تھوڑا سا غلط ہے (جیسے g00gle.com)",
        "یہ بہت لمبا ہے"
      ],
      "correct_index": 1,
      "category": "link_safety",
      "explanation": "ٹائپو اسکواٹنگ ایک عام حربہ ہے جس میں حملہ آور اصل ڈومینس سے ملتا جلتا لگتا ہے لیکن اس میں ہلکی سی غلطی ہوتی ہے۔"
    },
    {
      "id": 3,
      "question": "ایک ایس ایم ایس آپ کو 1000 ڈالر کی گفٹ کارڈ کی پیشکش کرتا ہے اگر آپ اپنا ای میل اور فون نمبر فراہم کریں۔ کیا یہ محفوظ ہے?",
      "options": [
        "ہاں، کمپنیاں اکثر گفٹ دیتی ہیں",
        "صرف اس صورت میں جب میسج میں آپ کا پورا نام شامل ہو",
        "نہیں، اگر یہ بہت اچھا لگتا ہے تو اس میں.probability ہے کہ یہ sach نہیں ہے"
      ],
      "correct_index": 2,
      "category": "personal_info",
      "explanation": "ناانوقع انعام کلاسک پھشنگ لورش ہیں جو آپ کی ذاتی معلومات چور کرنے کے لیے ڈیزائن کی جاتی ہیں۔"
    },
    {
      "id": 4,
      "question": "ایک کالر جو کہتا ہے کہ وہ آپ کے بینک کے 'فراڈ ڈیپارٹمنٹ' سے ہے وہ آپ سے آپ کے اکاؤنٹ کو محفوظ کرنے کے لیے ون ٹائم پاس ورڈ (OTP) مانگتا ہے۔ کیا آپ اسے دیتے ہیں?",
      "options": [
        "نہیں، بینک کبھی بھی کال پر OTP نہیں مانگتے",
        "ہاں، وہ میری مدد کر رہے ہیں",
        "صرف اس صورت میں جب وہ پہلے ہی سے آپ کے اکاؤنٹ نمبر جانتے ہوں"
      ],
      "correct_index": 0,
      "category": "banking",
      "explanation": "ون ٹائم پاس ورڈ (OTP) صرف آپ کی نظر کے لیے ہوتا ہے۔ بینک کبھی بھی کال پر OTP نہیں مانگے گا۔"
    },
    {
      "id": 5,
      "question": "ایک دوست آپ کو وہاٹس ایپ کے ذریعے 'مفت آئی فون गفٹ' کا لنک بھیجتا ہے جو 10 دوستوں کو آگے بھیجنے کا مطالبہ کرتا ہے۔ یہ کیا ہوسکتا ہے?",
      "options": [
        "یہ ایک وائرل مارکیٹنگ مہم ہے",
        "یہ ایک پھشنگ سکم ہے جو رابطے کی تفصیلات اکٹھا کرنے کے لیے",
        "یہ ایک بڑی کارپوریشن کی طرف سے ایک حقیقی تحفہ ہے"
      ],
      "correct_index": 1,
      "category": "social_engineering",
      "explanation": "بڑی数量 میں آگے بھیجے جانے والے 'گفٹ' لنکس اکثر 'سروے سکم' یا پھشنگ جال ہوتے ہیں۔"
    },
    {
      "id": 6,
      "question": "کتاک بینک کے لیے درج ذیل یو آر ایل میں سے کون سا محفوظ ہے?",
      "options": [
        "http://kotak-support-verify.com/login",
        "https://kotak.net/customer-update",
        "https://www.kotak.com/personal-banking"
      ],
      "correct_index": 2,
      "category": "link_safety",
      "explanation": "ہمیشہ بینک کا سرکاری ڈومین دیکھیں۔ بینکنگ کے لیے 'سپورٹ' یا '.net' جیسے متبادل ایکسٹینشن سے بچیں۔"
    },
    {
      "id": 7,
      "question": "آپ کو 'نیٹ فلکس' سے ایک ای میل ملتا ہے جو کہتا ہے کہ آپ کا پیمانہ ناکام ہوگیا ہے اور 2 گھنٹوں میں آپ کا اکاؤنٹ حذف ہوجائے گا۔ یہ کیا ہے?",
      "options": [
        "یہ بہت زیادہ جلدی ہے اور تھریٹ ہے",
        "ای میل میں نیٹ فلکس کا لوگو استعمال کیا گیا ہے",
        "ای میل 'ڈیئر کسٹمر' کے نام سے ہے"
      ],
      "correct_index": 0,
      "category": "social_engineering",
      "explanation": "ناکافی وقت کا خطرہ پھشنگ کا ایک کلاسک نفسیاتی حربہ ہے جو واضح سوچ کو روکتا ہے۔"
    },
    {
      "id": 8,
      "question": "کسی کو آپ کو 'payment وصولی' کے لیے ایک کیو آر کوڈ بھیجتا ہے جو آپ آن لائن بیچ رہے ہیں۔ کیا اس کو اسکین کرنا محفوظ ہے?",
      "options": [
        "ہاں، اسکینिंگ پیمانہ وصولی کے لیے ہے",
        "صرف اس صورت میں جب آپ ایک ویریفائیڈ پیمانہ ایپ استعمال کریں",
        "نہیں، کیو آر کوڈ اسکین کرنا پیمانہ بھیجنے کے لیے ہے، وصولی کے لیے نہیں"
      ],
      "correct_index": 2,
      "category": "banking",
      "explanation": "کیو آر کوڈز پیمانہ بھیجنے کے لیے ہیں۔ اگر کوئی آپ سے پیمانہ وصولی کے لیے کوڈ اسکین کرنے کو کہتا ہے تو یہ ایک سکم ہے۔"
    },
    {
      "id": 9,
      "question": "ایک پیغام کہتا ہے کہ آپ کے پاس 'Pending ٹیکس ری فنڈ' ہے اور آپ سے PAN اور بینک کے تفصیلات مانگتا ہے۔ آپ کیسے رد عمل دکھاتے ہیں?",
      "options": [
        "تفصیلات فراہم کریں تاکہ آپ ری فنڈ وصول کر سکیں",
        " اسے نظر انداز کریں؛ انکم ٹیکس محکمہ سرکاری پورٹل کا استعمال کرتا ہے، ایس ایم ایس نہیں",
        "چیک کریں کہ بھیجنے والے کا نمبر پیشہ ورانہ دکھائی دے رہا ہے"
      ],
      "correct_index": 1,
      "category": "personal_info",
      "explanation": "سرکاری ادارے کبھی بھی ایس ایم ایس کے ذریعے PAN یا بینک کی تفصیلات نہیں مانگتے۔"
    },
    {
      "id": 10,
      "question": "Vishing کا کیا مطلب ہے?",
      "options": [
        "فون کالوں کے ذریعے پھشنگ (Voice Phishing)",
        "ویڈیو پھشنگ",
        "visual پھشنگ"
      ],
      "correct_index": 0,
      "category": "social_engineering",
      "explanation": "Vishing فون کالوں کے ذریعے پھشنگ ہے جو لوگوں کو اپنی ذاتی معلومات دینے کے لیے دھوکہ دیتی ہے۔"
    },
    {
      "id": 11,
      "question": "آپ کو ایک لنک دکھائی دیتا ہے: 'https://paypال.com' (ایک خاص 'آ' کے ساتھ)۔ اس حملے کو کیا کہتے ہیں?",
      "options": [
        "کاراکٹر حملہ",
        "ہومو گراف حملہ",
        "لنک سوپنگ"
      ],
      "correct_index": 1,
      "category": "link_safety",
      "explanation": "ہومو گراف حملے مختلف ال्फابٹس کے ملتا جلتا حروف استعمال کرتے ہیں تاکہ ڈومینز کو نقلی بنایا جا سکے۔"
    },
    {
      "id": 12,
      "question": "ایک ریکروٹر آپ سے رابطہ کرتا ہے اور آپ کو 'گھر سے کام' کی اعلی تنخواہ والی نوکری کی پیشکش کرتا ہے جس کے لیے 'سیکیورٹی ڈپازٹ' کی ضرورت ہوتی ہے۔ کیا آپ ادا کرتے ہیں?",
      "options": [
        "ہاں، یہ ایک اچھی نوکری کے لیے چھوٹی سی قیمت ہے",
        "صرف اس صورت میں جب وہ پہلے معاہدہ فراہم کریں",
        "نہیں، حقیقی کمپنیاں ملازمت کے لیے پیسے نہیں مانگتی"
      ],
      "correct_index": 2,
      "category": "social_engineering",
      "explanation": "نوکری کے سکم اکثر 'ڈپازٹ' کا مطالبہ کرتے ہیں۔ حقیقی ملازمت دینے والے آپ کو ادا کرتے ہیں؛ آپ انہیں نہیں دیتے۔"
    },
    {
      "id": 13,
      "question": "اپنے باس آپ کو ایک ای میل بھیجتے ہیں جو کہتے ہیں کہ آپ کو گفٹ کارڈز خریدنی چاہیئں اور کوڈز بھیجنی چاہیئں۔ آپ کیا کرتے ہیں?",
      "options": [
        "براہِ کرم براہِ راست اپنے باس سے رابطہ کریں تاکہ مطالبہ کی تصدیق کی جا سکے",
        "فوری طور پر انہیں خریدیں تاکہ کارکردگی کا مظاہرہ کیا جا سکے",
        "پہلے کمپنی کا کرڈ مانگیں"
      ],
      "correct_index": 0,
      "category": "social_engineering",
      "explanation": "گفٹ کارڈ کے مطالبے 'بزنس ای میل کمپرومائز' کے سکم ہوتے ہیں۔ ہمیشہ دوسرے چینل کے ذریعے تصدیق کریں۔"
    },
    {
      "id": 14,
      "question": "ایک ایپ آپ سے اجازت مانگتی ہے تاکہ وہ آپ کے تمام ایس ایم ایس کو پڑھ سکے۔ کیا آپ اجازت دیتے ہیں?",
      "options": [
        "ہاں، بہت سے ایپ کو OTP کے لیے اس کی ضرورت ہوتی ہے",
        "نہیں، یہ بینک کے OTP چور کر سکتا ہے",
        "صرف اس صورت میں جب یہ پلے سٹور سے ہو"
      ],
      "correct_index": 1,
      "category": "personal_info",
      "explanation": "نقصان دہ ایپز ایس ایم ایس کی اجازت کا استعمال بینک کے OTP کو 'سننے' اور چور کرنے کے لیے کرتے ہیں۔"
    }
  ],
  "zh": [
    {
      "id": 1,
      "question": "你收到一条短收消息，说我你的银行资产被拒绝，带记不过要点击一个链接掌我见打诺！",
      "options": [
        "放忽消息，直接查看银行客户端",
        "点击链接掌要修流见打诺",
        "回复短收消息诲询详细"
      ],
      "correct_index": 0,
      "category": "banking",
      "explanation": "银行不会请您用链接掌见打诺，带记不过用单体端或网站"
    },
    {
      "id": 2,
      "question": "什一种索引是能过会拒绝的索引！",
      "options": [
        "使用'https://'",
        "域名是过住少的计传角（例子， g00gle.com）",
        "是能过长"
      ],
      "correct_index": 1,
      "category": "link_safety",
      "explanation": "职业拒绝所使用的拒绝方债，用体于真正的域名不起一些少的计传角"
    },
    {
      "id": 3,
      "question": "一条短收消息把而一个 $1000 礼莎卡社保用你的邮件和手机号码， 谁是起好的吗！",
      "options": [
        "是，公司带不要把而吗",
        "放忽手机号码，才认证",
        "不，如果走点英好，能过是你的我"
      ],
      "correct_index": 2,
      "category": "personal_info",
      "explanation": "拿成私服的把而是点一种汗影拒绝，用来拒绝你的一些信息"
    },
    {
      "id": 4,
      "question": "一个打升而为你的银行的拒绝部门，请您提供一下债券部修流见打诺， 你让他么见打诺！",
      "options": [
        "不，银行不会用打升请您提供一下债",
        "是，我们请您带不过我",
        "放忽手机号码，才认证"
      ],
      "correct_index": 0,
      "category": "banking",
      "explanation": "一下债券部修流见打诺是你们的私机，银行不会用打升请您提供一下债"
    },
    {
      "id": 5,
      "question": "一个朋友打升一个链接或而为运回一个‘苹回技肉’，要您切以与因一些朋友。 这是什么！",
      "options": [
        "一种网站投迄",
        "拒绝把而一个汗影拒绝",
        "一个单体端的礼莎"
      ],
      "correct_index": 1,
      "category": "social_engineering",
      "explanation": "邯一个‘技肉’的链接是点一种汗影拒绝，用来拒绝你的联系信息"
    },
    {
      "id": 6,
      "question": "什一个网址是最安全的！",
      "options": [
        "http://kotak-support-verify.com/login",
        "https://kotak.net/customer-update",
        "https://www.kotak.com/personal-banking"
      ],
      "correct_index": 2,
      "category": "link_safety",
      "explanation": "带记查看银行的单体域名，近体以外的域名"
    },
    {
      "id": 7,
      "question": "你收到一个邮件说我你的 Netflix 资产拒绝，带记不过要不起一些時間，为何！",
      "options": [
        "点一种一种点中汗影拒绝",
        "邮件使用 Netflix 图标",
        "邮件受以！而端体"
      ],
      "correct_index": 0,
      "category": "social_engineering",
      "explanation": "拒绝而点一种一种点中汗影受用，会拒绝你的私机"
    },
    {
      "id": 8,
      "question": "一个人发送一个 QR 码端为我而为你带不过提供消息， 你是忽略么见打诺！",
      "options": [
        "是，打升为收件了",
        "放忽手机号码，才认证",
        "不，打升为收件了"
      ],
      "correct_index": 2,
      "category": "banking",
      "explanation": "QR 码是用于提供了。如果一个人而为你提供一个 QR 码端为你收件，骆拒绝"
    },
    {
      "id": 9,
      "question": "一条短收消息说我你有一个索引的税拒绝资产，用你的邮件和银行资产信息， 你忽略么见打诺！",
      "options": [
        "填写信息",
        "放忽，政府部门使用单体端。不用短收消息",
        "查看受号格式"
      ],
      "correct_index": 1,
      "category": "personal_info",
      "explanation": "政府部门不会用短收消息请您提供信息"
    },
    {
      "id": 10,
      "question": "个见手机拒绝中，vishing 中的 v 要是什么！",
      "options": [
        "壁语拒绝",
        "视频拒绝",
        "观点拒绝"
      ],
      "correct_index": 0,
      "category": "social_engineering",
      "explanation": "vishing 是一种拒绝，用于手机请您提供信息"
    },
    {
      "id": 11,
      "question": "你查看一个链接：'https://paypаl.com'（中使用一个品级字符），这是什么种拒绝！",
      "options": [
        "字符拒绝",
        "一种汗影拒绝，用体于不同汗影网址",
        "链接换换"
      ],
      "correct_index": 1,
      "category": "link_safety",
      "explanation": "汗影拒绝用于不同汗影网址，会拒绝你的私机"
    }
  ],
  "ar": [
    {
      "id": 1,
      "question": "تستلم رسالة نصية تقول إن حسابك البنكي معلق و يجب عليك النقر على الرابط للتأكيد. ماذا تفعل؟",
      "options": [
        "تجاهل الرسالة وتتحقق من تطبيق البنك مباشرة",
        "انقر على الرابط على الفور لإصلاحه",
        "ارجع إلى الرسالة النصية واطلب المزيد من التفاصيل"
      ],
      "correct_index": 0,
      "category": "banking",
      "explanation": "البنوك لن تطلب أبدا التحقق من حسابك عبر رابط في رسالة نصية. استخدم دائما التطبيق الرسمي أو الموقع الإلكتروني."
    },
    {
      "id": 2,
      "question": "ما هو علامة على أن الرابط قد يكون مخادعا؟",
      "options": [
        "استخدام 'https://'",
        "اسم النطاق مشفر قليلا (على سبيل المثال ، g00gle.com)",
        "هو طويل جدا"
      ],
      "correct_index": 1,
      "category": "link_safety",
      "explanation": "Typosquatting هو تكتيك شائع يستخدم فيه المهاجمون نطاقات تشبه النطاقات الحقيقية ولكنها تحتوي على أخطاء دقيقة."
    },
    {
      "id": 3,
      "question": "تُرسل رسالة نصية لك تقدم لك بطاقة هدية بقيمة 1000 دولار إذاprovided بريدك الإلكتروني ورقم هاتفك. هل هذا آمن؟",
      "options": [
        "نعم ، تقوم الشركات دائما بالمسابقات",
        "فقط إذا كان الرسالة تتضمن اسمك الكامل",
        "لا ، إذا كان يبدو 太 جيدا ليكون صحيحا ، فهو احتمالا كاذبا"
      ],
      "correct_index": 2,
      "category": "personal_info",
      "explanation": "الجوائز غير المتوقعة هي خدع سمكة كلاسيكية مصممة لسرقة المعلومات الشخصية."
    },
    {
      "id": 4,
      "question": "يدعي المتصل أنه من \"قسم الاحتيال\" في بنكك ويسأل عن رسالة OTP لتأمين حسابك. هل تعطيه؟",
      "options": [
        "لا،البنوك لا تطلب أبدا كلمة المرور الفردية عبر الهاتف",
        "نعم،هم يحاولون مساعدتي",
        "فقط إذا كانوا يعرفون بالفعل رقم حسابي"
      ],
      "correct_index": 0,
      "category": "banking",
      "explanation": "كلمة المرور الفردية هي فقط لعيونك. البنوك لن تطلب أبدا منها عبر مكالمة هاتفية."
    },
    {
      "id": 5,
      "question": "يرسل لك صديق رابطًا عبر WhatsApp لجائزة \"هاتف أيفون مجاني\" يتطلب منه نقل الرابط إلى 10 أصدقاء. ما هو هذا على الأرجح؟",
      "options": [
        "حملة تسويقية فيروسية",
        "خدعة سمكة لجمع بيانات الاتصال",
        "هدية حقيقية من شركة كبيرة"
      ],
      "correct_index": 1,
      "category": "social_engineering",
      "explanation": "الروابط المنقولة على نطاق واسع souvent \"مسح أماني\" أو فخاخ سمكة."
    },
    {
      "id": 6,
      "question": "أي من هذه الروابط هو الأكثر أمانا لفتح Kotak Bank؟",
      "options": [
        "http://kotak-support-verify.com/login",
        "https://kotak.net/customer-update",
        "https://www.kotak.com/personal-banking"
      ],
      "correct_index": 2,
      "category": "link_safety",
      "explanation": "ابحث دائما عن النطاق الرسمي للبنك. تجنب \"دعم\" أو إضافات بديلة مثل \".net\" للوصول إلى البنك."
    },
    {
      "id": 7,
      "question": "تستلم رسالة إلكترونية من \"نيتفليكس\" تقول إن عملية الدفع فشلت وسيتم حذف حسابك في غضون ساعتين. ما هو العلامة الحمراء الرئيسية؟",
      "options": [
        "الاستعجال الشديد وتهديد الحذف",
        "تستخدم الرسالة الإلكترونية شعار نيتفليكس",
        "الرسالة الإلكترونية موجهة إلى 'الزملاء العزيزين'"
      ],
      "correct_index": 0,
      "category": "social_engineering",
      "explanation": "الاستعجال الصناعي هو خدعة نفسية كلاسيكية يستخدمها سمك النيتفليكس لمنع التفكير الواضح."
    },
    {
      "id": 8,
      "question": "يرسل لك شخص رمز QR \"لتلقي مدفوعات\" لعنصر تبيعه على الإنترنت. هل من الآمن مسح الرمز؟",
      "options": [
        "نعم ، مسح رمز QR هو لتلقي الأموال",
        "فقط إذا كنت تستخدم تطبيق مدفوعات تم التحقق منه",
        "لا ، مسح رمز QR هو لأغراض الدفع ، وليس لتلقي الأموال"
      ],
      "correct_index": 2,
      "category": "banking",
      "explanation": "رمز QR هو لإرسال الأموال. إذا طلب منك شخص مسح رمز QR لتلقي الأموال ، فهذا خدعة."
    },
    {
      "id": 9,
      "question": "الرسالة تقول إن لديك \"استرداد ضريبي معلق\" ويسألك عن PAN وبيانات البنك. كيف يجب أن تستجيب؟",
      "options": [
        "املأ البيانات للحصول على استردادك",
        "تجاهلها ؛ تستخدم الإدارة الرسمية البريديات ، وليس الرسائل النصية",
        "تحقق مما إذا كان رقم المرسل يبدو محترفًا"
      ],
      "correct_index": 1,
      "category": "personal_info",
      "explanation": "الوكالات الحكومية لا تطلب أبدا معلومات حساسة مثل PAN أو данные البنك عبر الرسائل النصية."
    },
    {
      "id": 10,
      "question": "ماذا يرمز إلى \"Vishing\"؟",
      "options": [
        "سمكة الصوت (السمكة عبر المكالمات الهاتفية)",
        "فيديو السمكة",
        "السمكة البصرية"
      ],
      "correct_index": 0,
      "category": "social_engineering",
      "explanation": "Vishing هي سمكة يتم إجراؤها عبر المكالمات الهاتفية لخداع الناس في إعطاء المعلومات الشخصية."
    },
    {
      "id": 11,
      "question": "ترى رابطا: 'https://paypаl.com' (مع حرف خاص 'а'). ماذا يسمى هذا الهجوم؟",
      "options": [
        "هجوم الحرف",
        "هجوم Homograph",
        "هجوم استبدال الرابط"
      ],
      "correct_index": 1,
      "category": "link_safety",
      "explanation": "هجمات Homograph تستخدم الأحرف المزيفة من الحروف المختلفة لتزوير النطاقات."
    },
    {
      "id": 12,
      "question": "ياتي موظف التوظيف ي предлож لك وظيفة \"اعمل من المنزل\" عالية الأجر تتطلب \"وديعة أمان\". هل تدفع؟",
      "options": [
        "نعم ، هذا ثمن صغير للوظيفة الجيدة",
        "فقط إذا قدموها لك عقدا أولا",
        "لا ، الشركات الحقيقية لا تطلب أبدا المال لتوظيفك"
      ],
      "correct_index": 2,
      "category": "social_engineering",
      "explanation": "خدع العمل thường تطلب \"الودائع\" في البداية. الشركات الحقيقية تدفع لك ؛ أنت لا تدفع لهم."
    },
    {
      "id": 13,
      "question": "يرسل لك رئيسك رسالة بريد إلكتروني يطلب منك شراء بطاقات هدايا وإرسال الرموز. ماذا يجب أن تفعل؟",
      "options": [
        "اتصال مباشر لرئيسك للتأكيد على الطلب",
        "شراءها على الفور لإظهار الكفاءة",
        "الطلب من بطاقة الائتمان للشركة أولا"
      ],
      "correct_index": 0,
      "category": "social_engineering",
      "explanation": "طلبات بطاقات الهدايا هي خدع شائعة \"إختراق البريد الإلكتروني للشركات\". حدد دائما عبر قناة أخرى."
    },
    {
      "id": 14,
      "question": "ytaleb تطبيق يطلب منك السماح له بقراءة جميع رسائل SMS الخاصة بك. هل يجب أن تسمح له بذلك؟",
      "options": [
        "نعم ، العديد من التطبيقات تحتاج إليها لعمليات OTP",
        "لا ، يمكن للتطبيقات الخبيثة استخدام إذن SMS لسرقة OTP البنكي الخاصة بك",
        "فقط إذا كان التطبيق من متجر Play"
      ],
      "correct_index": 1,
      "category": "personal_info",
      "explanation": "التطبيقات الخبيثة تستخدم إذن SMS \"لتحري\" وسرقة OTP البنكي."
    },
    {
      "id": 15,
      "question": "إذا أدخلت كلمة المرور الخاصة بك عن طريق الخطأ على موقع سمكة ، ما هو الخطوة الرئيسية الأولى التي يجب اتخاذها؟",
      "options": [
        "اتصال الشرطة",
        "الانتظار ومعرفة ما إذا كان شيء ما سيحصل",
        "تغيير كلمة المرور على الفور على الموقع الحقيقي"
      ],
      "correct_index": 2,
      "category": "personal_info",
      "explanation": "السرعة هي المفتاح. تغيير كلمة المرور الخاصة بك على الفور يمكن أن يمنع المهاجم من الدخول."
    }
  ],
  "fr": [
    {
      "id": 1,
      "question": "Vous recevez un SMS disant que votre compte bancaire est suspendu et que vous devez cliquer sur un lien pour le vérifier. Que faites-vous ?",
      "options": [
        "Ignorez le message et vérifiez directement votre application bancaire",
        "Cliquez sur le lien immédiatement pour le réparer",
        "Répondez au SMS en demandant des détails"
      ],
      "correct_index": 0,
      "category": "banking",
      "explanation": "Les banques ne vous demanderont jamais de vérifier votre compte via un lien dans un SMS. Utilisez toujours l'application ou le site officiel."
    },
    {
      "id": 2,
      "question": "Quel est un signe qu'un lien pourrait être malveillant ?",
      "options": [
        "Il utilise 'https://'",
        "Le nom de domaine est légèrement mal orthographié (par exemple, g00gle.com)",
        "Il est très long"
      ],
      "correct_index": 1,
      "category": "link_safety",
      "explanation": "Le typosquatting est une tactique courante où les attaquants utilisent des domaines qui ressemblent à des vrais mais comportent des erreurs subtiles."
    },
    {
      "id": 3,
      "question": "Un SMS vous offre une carte-cadeau de 1 000 $ si vous fournissez votre adresse e-mail et votre numéro de téléphone. Est-ce sécuritaire ?",
      "options": [
        "Oui, les entreprises font des concours toute la temps",
        "Seulement si le message inclut votre nom complet",
        "Non, si cela semble trop beau pour être vrai, cela l'est probablement"
      ],
      "correct_index": 2,
      "category": "personal_info",
      "explanation": "Les prix inattendus sont des appâts de phishing classiques conçus pour voler vos informations personnelles."
    },
    {
      "id": 4,
      "question": "Un appelant prétendant être du 'département de la fraude' de votre banque vous demande un OTP pour sécuriser votre compte. Le donnez-vous ?",
      "options": [
        "Non, les banques ne demandent jamais d'OTP par téléphone",
        "Oui, ils essayent de m'aider",
        "Seulement si ils connaissent déjà mon numéro de compte"
      ],
      "correct_index": 0,
      "category": "banking",
      "explanation": "Un OTP (mot de passe à usage unique) est pour vos yeux seulement. Les banques ne vous le demanderont jamais par téléphone."
    },
    {
      "id": 5,
      "question": "Un ami vous envoie un lien via WhatsApp pour un 'Concours de l'iPhone gratuit' qui nécessite de le transmettre à 10 amis. Qu'est-ce que cela est susceptible d'être ?",
      "options": [
        "Une campagne de marketing virale",
        "Un piège de phishing pour collecter des coordonnées",
        "Un véritable cadeau d'une grande entreprise"
      ],
      "correct_index": 1,
      "category": "social_engineering",
      "explanation": "Les liens de concours massivement transmis sont souvent des 'arnaques de sondages' ou des pièges de phishing."
    },
    {
      "id": 6,
      "question": "Lequel de ces URL est le plus sûr à cliquer pour la banque Kotak ?",
      "options": [
        "http://kotak-support-verify.com/login",
        "https://kotak.net/customer-update",
        "https://www.kotak.com/personal-banking"
      ],
      "correct_index": 2,
      "category": "link_safety",
      "explanation": "Recherchez toujours le domaine officiel de la banque. Évitez les extensions 'support' ou alternatives comme '.net' pour la banque."
    },
    {
      "id": 7,
      "question": "Vous recevez un e-mail de 'Netflix' indiquant que votre paiement a échoué et que votre compte sera supprimé dans 2 heures. Quel est le principal drapeau rouge ?",
      "options": [
        "L'extrême urgence et la menace de suppression",
        "L'e-mail utilise le logo de Netflix",
        "L'e-mail est adressé 'Cher client'"
      ],
      "correct_index": 0,
      "category": "social_engineering",
      "explanation": "L'urgence artificielle est un piège psychologique classique utilisé par les phishers pour empêcher la réflexion claire."
    },
    {
      "id": 8,
      "question": "Quelqu'un vous envoie un code QR pour 'recevoir un paiement' pour un article que vous vendez en ligne. Est-il sécuritaire de le scanner ?",
      "options": [
        "Oui, la scanographie est pour recevoir de l'argent",
        "Seulement si vous utilisez une application de paiement vérifiée",
        "Non, la scanographie d'un code QR est pour effectuer des paiements, et non pour les recevoir"
      ],
      "correct_index": 2,
      "category": "banking",
      "explanation": "Les codes QR sont pour ENVOYER de l'argent. Si quelqu'un vous demande de scanner un code pour recevoir de l'argent, c'est une arnaque."
    },
    {
      "id": 9,
      "question": "Un message prétend que vous avez un 'remboursement d'impôt en attente' et demande votre PAN et vos coordonnées bancaires. Comment réagissez-vous ?",
      "options": [
        "Remplissez les détails pour obtenir votre remboursement",
        "Ignorez-le ; le département des impôts utilise des portails officiels, et non des SMS",
        "Vérifiez si le numéro de l'expéditeur semble professionnel"
      ],
      "correct_index": 1,
      "category": "personal_info",
      "explanation": "Les agences gouvernementales ne demandent jamais d'informations sensibles comme le PAN ou les coordonnées bancaires via SMS."
    },
    {
      "id": 10,
      "question": "Que signifie 'Vishing' ?",
      "options": [
        "Phishing vocal (phishing par appel téléphonique)",
        "Phishing vidéo",
        "Phishing visuel"
      ],
      "correct_index": 0,
      "category": "social_engineering",
      "explanation": "Le vishing est un phishing effectué par appel téléphonique pour tromper les gens et leur faire divulguer des informations personnelles."
    },
    {
      "id": 11,
      "question": "Vous voyez un lien : 'https://paypаl.com' (avec un 'а' spécial). Quel est le nom de cette attaque ?",
      "options": [
        "Attaque de caractère",
        "Attaque d'homographe",
        "Attaque d'échange de lien"
      ],
      "correct_index": 1,
      "category": "link_safety",
      "explanation": "Les attaques d'homographe utilisent des caractères similaires provenant d'alphabets différents pour usurper des domaines."
    },
    {
      "id": 12,
      "question": "Un recruteur vous contacte pour vous offrir un emploi 'Travail à domicile' bien rémunéré qui nécessite un 'dépôt de sécurité'. Le payez-vous ?",
      "options": [
        "Oui, c'est un petit prix pour un bon emploi",
        "Seulement si ils vous fournissent un contrat d'abord",
        "Non, les entreprises réelles ne demandent jamais d'argent pour vous embaucher"
      ],
      "correct_index": 2,
      "category": "social_engineering",
      "explanation": "Les arnaques d'emploi demandent souvent des 'dépôts' à l'avance. Les employeurs réels vous paient ; vous ne les payez pas."
    },
    {
      "id": 13,
      "question": "Votre patron vous envoie un e-mail urgent vous demandant d'acheter des cartes-cadeaux et de lui envoyer les codes. Que devez-vous faire ?",
      "options": [
        "Appelez votre patron directement pour confirmer la demande",
        "Achetez-les immédiatement pour montrer votre efficacité",
        "Demandez la carte de crédit de l'entreprise d'abord"
      ],
      "correct_index": 0,
      "category": "social_engineering",
      "explanation": "Les demandes de cartes-cadeaux sont des arnaques de 'Compromission d'e-mail d'entreprise' courantes. Vérifiez toujours via un autre canal."
    },
    {
      "id": 14,
      "question": "Une application demande l'autorisation de lire tous vos SMS. Devriez-vous l'autoriser ?",
      "options": [
        "Oui, de nombreuses applications en ont besoin pour les OTP",
        "Non, cela pourrait voler vos OTP de banque à mesure qu'ils arrivent",
        "Seulement si c'est à partir du Play Store"
      ],
      "correct_index": 1,
      "category": "personal_info",
      "explanation": "Les applications malveillantes utilisent les autorisations de SMS pour 'renifler' et voler les OTP de banque."
    },
    {
      "id": 15,
      "question": "Si vous avez accidentellement saisi votre mot de passe sur un site de phishing, quelle est la première étape critique ?",
      "options": [
        "Appelez la police",
        "Attendez et voyez si quelque chose se passe",
        "Changez votre mot de passe immédiatement sur le site réel"
      ],
      "correct_index": 2,
      "category": "personal_info",
      "explanation": "La vitesse est essentielle. Changer votre mot de passe immédiatement peut verrouiller l'accès de l'attaquant."
    }
  ],
  "de": [
    {
      "id": 1,
      "question": "Sie erhalten eine SMS, in der steht, dass Ihr Bankkonto gesperrt ist und Sie einen Link anklicken müssen, um es zu bestätigen. Was tun Sie?",
      "options": [
        "Ich ignoriere die Nachricht und überprüfe direkt meine Bank-App",
        "Ich klicke sofort auf den Link, um es zu beheben",
        "Ich antworte auf die SMS und bitte um Details"
      ],
      "correct_index": 0,
      "category": "banking",
      "explanation": "Banken werden Sie niemals auffordern, Ihr Konto über einen Link in einer SMS zu bestätigen. Verwenden Sie immer die offizielle App oder Website."
    },
    {
      "id": 2,
      "question": "Was ist ein Zeichen dafür, dass ein Link möglicherweise schädlich ist?",
      "options": [
        "Er verwendet 'https://'",
        "Der Domain-Name ist leicht fehlerhaft (z. B. g00gle.com)",
        "Er ist sehr lang"
      ],
      "correct_index": 1,
      "category": "link_safety",
      "explanation": "Typosquatting ist eine gängige Taktik, bei der Angreifer Domains verwenden, die wie echte aussehen, aber feine Fehler enthalten."
    },
    {
      "id": 3,
      "question": "Eine SMS bietet Ihnen eine 1.000-Dollar-Geschenkkarte an, wenn Sie Ihre E-Mail-Adresse und Telefonnummer angeben. Ist das sicher?",
      "options": [
        "Ja, Unternehmen veranstalten ständig Gewinnspiele",
        "Nur wenn die Nachricht Ihren vollen Namen enthält",
        "Nein, wenn es zu gut klingt, um wahr zu sein, ist es wahrscheinlich nicht wahr"
      ],
      "correct_index": 2,
      "category": "personal_info",
      "explanation": "Unerwartete Gewinne sind klassische Phishing-Köder, die darauf abzielen, Ihre persönlichen Informationen zu stehlen."
    },
    {
      "id": 4,
      "question": "Ein Anrufer, der vorgibt, von der „Betrugsabteilung“ Ihrer Bank zu sein, bittet um einen OTP, um Ihr Konto zu sichern. Geben Sie ihn?",
      "options": [
        "Nein, Banken fragen niemals nach OTPs am Telefon",
        "Ja, sie versuchen, mir zu helfen",
        "Nur wenn sie bereits meine Kontonummer kennen"
      ],
      "correct_index": 0,
      "category": "banking",
      "explanation": "Ein OTP (One-Time-Password) ist nur für Ihre Augen bestimmt. Banken werden niemals nach einem OTP am Telefon fragen."
    },
    {
      "id": 5,
      "question": "Ein Freund sendet Ihnen über WhatsApp einen Link für ein 'Free iPhone Gewinnspiel', das es erfordert, ihn an 10 Freunde weiterzuleiten. Was ist das wahrscheinlich?",
      "options": [
        "Eine Viral-Marketing-Kampagne",
        "Ein Phishing-Angriff, um Kontaktdaten zu sammeln",
        "Ein echtes Geschenk von einem großen Konzern"
      ],
      "correct_index": 1,
      "category": "social_engineering",
      "explanation": "Massenweise weitergeleitete 'Gewinnspiel'-Links sind oft 'Umfragenschwindel' oder Phishing-Fallen."
    },
    {
      "id": 6,
      "question": "Welche dieser URLs ist am sichersten, um auf die Kotak-Bank zuzugreifen?",
      "options": [
        "http://kotak-support-verify.com/login",
        "https://kotak.net/customer-update",
        "https://www.kotak.com/personal-banking"
      ],
      "correct_index": 2,
      "category": "link_safety",
      "explanation": "Suchen Sie immer nach der offiziellen Domain der Bank. Vermeiden Sie 'Support'- oder alternative Erweiterungen wie '.net' für das Online-Banking."
    },
    {
      "id": 7,
      "question": "Sie erhalten eine E-Mail von 'Netflix', in der steht, dass Ihre Zahlung fehlgeschlagen ist und Ihr Konto in 2 Stunden gelöscht wird. Welche ist die Hauptwarnung?",
      "options": [
        "Die extreme Dringlichkeit und die Drohung mit Löschung",
        "Die E-Mail verwendet das Netflix-Logo",
        "Die E-Mail ist an 'Sehr geehrter Kunde' adressiert"
      ],
      "correct_index": 0,
      "category": "social_engineering",
      "explanation": "Künstliche Dringlichkeit ist ein klassischer psychologischer Trick, der von Phishern verwendet wird, um klares Denken zu verhindern."
    },
    {
      "id": 8,
      "question": "Jemand sendet Ihnen einen QR-Code, um 'eine Zahlung zu erhalten' für ein Artikel, den Sie online verkaufen. Ist es sicher, den Code zu scannen?",
      "options": [
        "Ja, Scannen ist zum Empfangen von Geld",
        "Nur wenn Sie eine verifizierte Zahlungs-App verwenden",
        "Nein, das Scannen eines QR-Codes ist zum Bezahlen, nicht zum Empfangen"
      ],
      "correct_index": 2,
      "category": "banking",
      "explanation": "QR-Codes sind zum SENDEN von Geld. Wenn jemand Sie auffordert, einen Code zu scannen, um Geld zu erhalten, ist es ein Betrug."
    },
    {
      "id": 9,
      "question": "Eine Nachricht behauptet, dass Sie eine 'ausstehende Steuererstattung' haben und bittet um Ihre PAN und Bankdetails. Wie sollten Sie reagieren?",
      "options": [
        "Ich fülle die Details aus, um meine Erstattung zu erhalten",
        "Ich ignoriere es; die IT-Abteilung verwendet offizielle Portale, keine SMS",
        "Ich überprüfe, ob die Rufnummer des Absenders professionell aussieht"
      ],
      "correct_index": 1,
      "category": "personal_info",
      "explanation": "Regierungsbehörden fragen niemals nach sensiblen Informationen wie PAN oder Bankdetails per SMS."
    },
    {
      "id": 10,
      "question": "Wofür steht 'Vishing'?",
      "options": [
        "Voice Phishing (Phishing über Telefonanrufe)",
        "Video Phishing",
        "Visuelles Phishing"
      ],
      "correct_index": 0,
      "category": "social_engineering",
      "explanation": "Vishing ist Phishing, das über Telefonanrufe durchgeführt wird, um Menschen dazu zu bringen, persönliche Informationen preiszugeben."
    },
    {
      "id": 11,
      "question": "Sie sehen einen Link: 'https://paypаl.com' (mit einem speziellen 'а'). Was ist dieser Angriff genannt?",
      "options": [
        "Zeichenangriff",
        "Homograph-Angriff",
        "Link-Tausch"
      ],
      "correct_index": 1,
      "category": "link_safety",
      "explanation": "Homograph-Angriffe verwenden ähnlich aussehende Zeichen aus verschiedenen Alphabeten, um Domains zu spoofen."
    },
    {
      "id": 12,
      "question": "Ein Recruiter kontaktiert Sie und bietet Ihnen einen hochbezahlten 'Work-from-Home'-Job an, der einen 'Sicherheitsaufschlag' erfordert. Zahlen Sie?",
      "options": [
        "Ja, es ist ein kleiner Preis für einen guten Job",
        "Nur wenn sie einen Vertrag vorlegen",
        "Nein, echte Unternehmen verlangen niemals Geld, um jemanden einzustellen"
      ],
      "correct_index": 2,
      "category": "social_engineering",
      "explanation": "Jobbetrug erfordert oft 'Aufschläge' im Voraus. Echte Arbeitgeber zahlen Ihnen; Sie zahlen ihnen nicht."
    },
    {
      "id": 13,
      "question": "Ihr Chef sendet Ihnen eine dringende E-Mail, in der er Sie auffordert, Geschenkkarten zu kaufen und die Codes zu senden. Was sollten Sie tun?",
      "options": [
        "Ich rufe meinen Chef direkt an, um die Anfrage zu bestätigen",
        "Ich kaufe sie sofort, um Effizienz zu zeigen",
        "Ich frage nach der Firmencreditkarte"
      ],
      "correct_index": 0,
      "category": "social_engineering",
      "explanation": "Geschenkkartenanfragen sind üblicher 'Business-E-Mail-Compromise'-Betrug. Bestätigen Sie immer über einen anderen Kanal."
    },
    {
      "id": 14,
      "question": "Eine App bittet um die Erlaubnis, alle Ihre SMS-Nachrichten zu lesen. Sollten Sie dies erlauben?",
      "options": [
        "Ja, viele Apps benötigen dies für OTPs",
        "Nein, es könnte Ihre Bank-OTPs stehlen, wenn diese ankommen",
        "Nur wenn es aus dem Play Store stammt"
      ],
      "correct_index": 1,
      "category": "personal_info",
      "explanation": "Schädliche Apps nutzen SMS-Berechtigungen, um Bank-OTPs zu 'schnüffeln' und zu stehlen."
    },
    {
      "id": 15,
      "question": "Wenn Sie versehentlich Ihr Passwort auf einer Phishing-Website eingegeben haben, was ist der erste kritische Schritt?",
      "options": [
        "Ich rufe die Polizei",
        "Ich warte und sehe, ob etwas passiert",
        "Ich ändere mein Passwort sofort auf der echten Website"
      ],
      "correct_index": 2,
      "category": "personal_info",
      "explanation": "Geschwindigkeit ist der Schlüssel. Das sofortige Ändern Ihres Passworts kann den Angreifer aussperren."
    }
  ],
  "ja": [
    {
      "id": 1,
      "question": "",
      "options": [
        "",
        "",
        ""
      ],
      "correct_index": 0,
      "category": "banking",
      "explanation": ""
    },
    {
      "id": 2,
      "question": "",
      "options": [
        "https://",
        "(g00gle.com)",
        ""
      ],
      "correct_index": 1,
      "category": "link_safety",
      "explanation": ""
    },
    {
      "id": 3,
      "question": "1,000",
      "options": [
        "",
        "",
        ""
      ],
      "correct_index": 2,
      "category": "personal_info",
      "explanation": ""
    },
    {
      "id": 4,
      "question": "OTP",
      "options": [
        "OTP",
        "",
        ""
      ],
      "correct_index": 0,
      "category": "banking",
      "explanation": "OTP"
    },
    {
      "id": 5,
      "question": "Free iPhone",
      "options": [
        "",
        "",
        ""
      ],
      "correct_index": 1,
      "category": "social_engineering",
      "explanation": ""
    },
    {
      "id": 6,
      "question": "Kotak",
      "options": [
        "http://kotak-support-verify.com/login",
        "https://kotak.net/customer-update",
        "https://www.kotak.com/personal-banking"
      ],
      "correct_index": 2,
      "category": "link_safety",
      "explanation": "Kotak"
    },
    {
      "id": 7,
      "question": "Netflix2",
      "options": [
        "",
        "Netflix",
        ""
      ],
      "correct_index": 0,
      "category": "social_engineering",
      "explanation": ""
    },
    {
      "id": 8,
      "question": "QR",
      "options": [
        "QR",
        "QR",
        "QR"
      ],
      "correct_index": 2,
      "category": "banking",
      "explanation": "QR"
    },
    {
      "id": 9,
      "question": "",
      "options": [
        "",
        "",
        ""
      ],
      "correct_index": 1,
      "category": "personal_info",
      "explanation": ""
    },
    {
      "id": 10,
      "question": "Vishing",
      "options": [
        "",
        "",
        ""
      ],
      "correct_index": 0,
      "category": "social_engineering",
      "explanation": "Vishing"
    },
    {
      "id": 11,
      "question": "https://payаl.com(а)",
      "options": [
        "",
        "",
        ""
      ],
      "correct_index": 1,
      "category": "link_safety",
      "explanation": ""
    },
    {
      "id": 12,
      "question": "",
      "options": [
        "",
        "",
        ""
      ],
      "correct_index": 2,
      "category": "social_engineering",
      "explanation": ""
    },
    {
      "id": 13,
      "question": "",
      "options": [
        "",
        "",
        ""
      ],
      "correct_index": 0,
      "category": "social_engineering",
      "explanation": ""
    },
    {
      "id": 14,
      "question": "SMS",
      "options": [
        "SMS",
        "SMS",
        ""
      ],
      "correct_index": 1,
      "category": "personal_info",
      "explanation": "SMS"
    },
    {
      "id": 15,
      "question": "",
      "options": [
        "",
        "",
        ""
      ],
      "correct_index": 2,
      "category": "personal_info",
      "explanation": ""
    }
  ],
  "pt": [
    {
      "id": 1,
      "question": "Você recebe uma mensagem de SMS dizendo que sua conta bancária foi suspensa e você deve clicar em um link para verificar. O que você faz?",
      "options": [
        "Ignorar a mensagem e verificar o aplicativo bancário diretamente",
        "Clicar no link imediatamente para consertar",
        "Responder à mensagem de SMS pedindo detalhes"
      ],
      "correct_index": 0,
      "category": "banking",
      "explanation": "Bancos nunca pedirão que você verifique sua conta via link em uma mensagem de SMS. Sempre use o aplicativo ou site oficial."
    },
    {
      "id": 2,
      "question": "Qual é um sinal de que um link pode ser malicioso?",
      "options": [
        "Ele usa 'https://'",
        "O nome de domínio está ligeiramente errado (por exemplo, g00gle.com)",
        "Ele é muito longo"
      ],
      "correct_index": 1,
      "category": "link_safety",
      "explanation": "Typosquatting é uma tática comum onde os atacantes usam domínios que parecem reais, mas têm erros sutis."
    },
    {
      "id": 3,
      "question": "Uma mensagem de SMS oferece um cartão de presente de $1.000 se você fornecer seu e-mail e número de telefone. Isso é seguro?",
      "options": [
        "Sim, as empresas fazem sorteios o tempo todo",
        "Somente se a mensagem incluir seu nome completo",
        "Não, se parecer bom demais para ser verdade, provavelmente é"
      ],
      "correct_index": 2,
      "category": "personal_info",
      "explanation": "Prêmios inesperados são iscas clássicas de phishing projetadas para roubar suas informações pessoais."
    },
    {
      "id": 4,
      "question": "Um chamador que se diz ser do 'departamento de fraude' do seu banco pede um OTP para segurar sua conta. Você fornece?",
      "options": [
        "Não, os bancos nunca pedem OTPs por telefone",
        "Sim, eles estão tentando me ajudar",
        "Somente se eles já souberem meu número de conta"
      ],
      "correct_index": 0,
      "category": "banking",
      "explanation": "Um OTP (senha de uso único) é para os seus olhos apenas. Os bancos nunca pedirão por ele em uma ligação."
    },
    {
      "id": 5,
      "question": "Um amigo envia um link via WhatsApp para um 'Sorteio de iPhone Grátis' que exige que você o envie para 10 amigos. O que é isso provavelmente?",
      "options": [
        "Uma campanha de marketing viral",
        "Um golpe de phishing para coletar detalhes de contato",
        "Um presente genuíno de uma grande corporação"
      ],
      "correct_index": 1,
      "category": "social_engineering",
      "explanation": "Links de 'sorteio' encaminhados em massa são frequentemente 'golpes de pesquisa' ou armadilhas de phishing."
    },
    {
      "id": 6,
      "question": "Qual desses URLs é o mais seguro para clicar no Kotak Bank?",
      "options": [
        "http://kotak-suporte-verificar.com/login",
        "https://kotak.net/atualizacao-do-cliente",
        "https://www.kotak.com/banco-personal"
      ],
      "correct_index": 2,
      "category": "link_safety",
      "explanation": "Sempre procure o domínio oficial do banco. Evite 'suporte' ou extensões alternativas como '.net' para bancos."
    },
    {
      "id": 7,
      "question": "Você recebe um e-mail da 'Netflix' dizendo que seu pagamento falhou e sua conta será excluída em 2 horas. Qual é a principal bandeira vermelha?",
      "options": [
        "A urgência extrema e a ameaça de exclusão",
        "O e-mail usa o logotipo da Netflix",
        "O e-mail é endereçado 'Prezado Cliente'"
      ],
      "correct_index": 0,
      "category": "social_engineering",
      "explanation": "Urgência artificial é um truque psicológico clássico usado por phishers para evitar o pensamento claro."
    },
    {
      "id": 8,
      "question": "Alguém envia um código QR para 'receber um pagamento' por um item que você está vendendo online. É seguro scanners?",
      "options": [
        "Sim, o scanner é para receber dinheiro",
        "Somente se você usar um aplicativo de pagamento verificado",
        "Não, o scanner de código QR é para enviar dinheiro, não para receber"
      ],
      "correct_index": 2,
      "category": "banking",
      "explanation": "Códigos QR são para ENVIAR dinheiro. Se alguém pedir que você scanner um código para receber dinheiro, é um golpe."
    },
    {
      "id": 9,
      "question": "Uma mensagem afirma que você tem um 'reembolso de imposto pendente' e pede seu PAN e detalhes bancários. Como você responde?",
      "options": [
        "Preencher os detalhes para receber o reembolso",
        "Ignorar; o departamento de IT usa portais oficiais, não SMS",
        "Verificar se o número do remetente parece profissional"
      ],
      "correct_index": 1,
      "category": "personal_info",
      "explanation": "Agências governamentais nunca pedem informações sensíveis como PAN ou detalhes bancários via SMS."
    },
    {
      "id": 10,
      "question": "O que 'Vishing' significa?",
      "options": [
        "Phishing de voz (phishing por meio de chamadas telefônicas)",
        "Phishing de vídeo",
        "Phishing visual"
      ],
      "correct_index": 0,
      "category": "social_engineering",
      "explanation": "Vishing é phishing conduzido por meio de chamadas telefônicas para enganar as pessoas a darem suas informações pessoais."
    },
    {
      "id": 11,
      "question": "Você vê um link: 'https://paypаl.com' (com um caractere especial 'а'). Qual é o nome desse ataque?",
      "options": [
        "Ataque de caractere",
        "Ataque de homógrafo",
        "Troca de link"
      ],
      "correct_index": 1,
      "category": "link_safety",
      "explanation": "Ataques de homógrafo usam caracteres semelhantes de diferentes alfabetos para falsificar domínios."
    },
    {
      "id": 12,
      "question": "Um recrutador entra em contato com você, oferecendo um emprego 'Trabalho em casa' bem remunerado que exige um 'depósito de segurança'. Você paga?",
      "options": [
        "Sim, é um preço pequeno por um bom emprego",
        "Somente se eles fornecerem um contrato primeiro",
        "Não, empresas reais nunca pedem dinheiro para contratar você"
      ],
      "correct_index": 2,
      "category": "social_engineering",
      "explanation": "Golpes de emprego frequentemente pedem 'depósitos' antecipados. Empregadores reais pagam a você; você não paga a eles."
    },
    {
      "id": 13,
      "question": "Seu chefe envia um e-mail urgente pedindo que você compre cartões de presente e envie os códigos. O que você deve fazer?",
      "options": [
        "Ligue para seu chefe diretamente para confirmar o pedido",
        "Compre-os imediatamente para mostrar eficiência",
        "Peça o cartão de crédito da empresa primeiro"
      ],
      "correct_index": 0,
      "category": "social_engineering",
      "explanation": "Pedidos de cartões de presente são comuns em golpes de 'Comprometimento de e-mail empresarial'. Sempre verifique por meio de outro canal."
    },
    {
      "id": 14,
      "question": "Um aplicativo pede permissão para ler todas as suas mensagens de SMS. Você deve permitir?",
      "options": [
        "Sim, muitos aplicativos precisam disso para OTPs",
        "Não, isso pode roubar seus OTPs bancários à medida que chegam",
        "Somente se for do Play Store"
      ],
      "correct_index": 1,
      "category": "personal_info",
      "explanation": "Aplicativos mal-intencionados usam permissões de SMS para 'snifar' e roubar OTPs bancários."
    },
    {
      "id": 15,
      "question": "Se você digitou sua senha em um site de phishing por engano, qual é a primeira etapa crítica?",
      "options": [
        "Ligue para a polícia",
        "Espere e veja se algo acontece",
        "Mude sua senha imediatamente no site real"
      ],
      "correct_index": 2,
      "category": "personal_info",
      "explanation": "A velocidade é a chave. Mudar sua senha imediatamente pode travar o atacante."
    }
  ],
  "es": [
    {
      "id": 1,
      "question": "Recibes un SMS que dice que tu cuenta bancaria está suspendida y debes hacer clic en un enlace para verificar. ¿Qué haces?",
      "options": [
        "Ignorar el mensaje y verificar directamente en la aplicación bancaria",
        "Hacer clic en el enlace de inmediato para solucionarlo",
        "Responder al SMS pidiendo detalles"
      ],
      "correct_index": 0,
      "category": "banking",
      "explanation": "Los bancos nunca piden que verifiques tu cuenta a través de un enlace en un SMS. Siempre usa la aplicación o sitio web oficial."
    },
    {
      "id": 2,
      "question": "¿Cuál es un signo de que un enlace podría ser malicioso?",
      "options": [
        "Utiliza 'https://'",
        "El nombre de dominio está ligeramente mal escrito (por ejemplo, g00gle.com)",
        "Es muy largo"
      ],
      "correct_index": 1,
      "category": "link_safety",
      "explanation": "El 'typosquatting' es una táctica común donde los atacantes usan dominios que se parecen a los reales pero tienen errores sutiles."
    },
    {
      "id": 3,
      "question": "Un SMS te ofrece una tarjeta de regalo de $1,000 si proporcionas tu correo electrónico y número de teléfono. ¿Es seguro?",
      "options": [
        "Sí, las empresas hacen sorteos todo el tiempo",
        "Sólo si el mensaje incluye tu nombre completo",
        "No, si suena demasiado bueno para ser verdad, probablemente no lo sea"
      ],
      "correct_index": 2,
      "category": "personal_info",
      "explanation": "Los premios inesperados son señuelos clásicos de phishing diseñados para robar tu información personal."
    },
    {
      "id": 4,
      "question": "Un llamador que dice ser del 'departamento de fraude' de tu banco te pide un OTP para asegurar tu cuenta. ¿Lo das?",
      "options": [
        "No, los bancos nunca piden OTPs por teléfono",
        "Sí, están tratando de ayudarme",
        "Sólo si ya conocen mi número de cuenta"
      ],
      "correct_index": 0,
      "category": "banking",
      "explanation": "Un OTP (Contraseña de un solo uso) es solo para tus ojos. Los bancos nunca piden que lo compartas en una llamada."
    },
    {
      "id": 5,
      "question": "Un amigo te envía un enlace a través de WhatsApp para un 'Sorteo de iPhone gratuito' que requiere que lo envíes a 10 amigos. ¿Qué es probable que sea?",
      "options": [
        "Una campaña de marketing viral",
        "Un timo de phishing para recopilar detalles de contacto",
        "Un regalo genuino de una gran corporación"
      ],
      "correct_index": 1,
      "category": "social_engineering",
      "explanation": "Los enlaces 'sorteos' que se envían en masa a menudo son 'estafas de encuestas' o trampas de phishing."
    },
    {
      "id": 6,
      "question": "¿Cuál de estos URLs es el más seguro para hacer clic en el Banco Kotak?",
      "options": [
        "http://kotak-soporte-verificar.com/iniciar-sesión",
        "https://kotak.net/actualización-del-cliente",
        "https://www.kotak.com/banca-personal"
      ],
      "correct_index": 2,
      "category": "link_safety",
      "explanation": "Siempre busca el dominio oficial del banco. Evita 'soporte' o extensiones alternativas como '.net' para la banca."
    },
    {
      "id": 7,
      "question": "Recibes un correo electrónico de 'Netflix' que dice que tu pago ha fallado y tu cuenta será eliminada en 2 horas. ¿Cuál es la principal señal de alerta?",
      "options": [
        "La extrema urgencia y la amenaza de eliminación",
        "El correo electrónico utiliza el logotipo de Netflix",
        "El correo electrónico está dirigido 'Estimado Cliente'"
      ],
      "correct_index": 0,
      "category": "social_engineering",
      "explanation": "La urgencia artificial es un truco psicológico clásico utilizado por los pescadores para evitar el pensamiento claro."
    },
    {
      "id": 8,
      "question": "Alguien te envía un código QR para 'recibir un pago' por un artículo que estás vendiendo en línea. ¿Es seguro escanearlo?",
      "options": [
        "Sí, escanear es para recibir dinero",
        "Sólo si usas una aplicación de pago verificada",
        "No, escanear un código QR es para realizar pagos, no para recibir"
      ],
      "correct_index": 2,
      "category": "banking",
      "explanation": "Los códigos QR son para ENVIAR dinero. Si alguien te pide que escanees un código para recibir dinero, es un fraude."
    },
    {
      "id": 9,
      "question": "Un mensaje afirma que tienes una 'devolución de impuestos pendiente' y te pide tu PAN y detalles bancarios. ¿Cómo deberías responder?",
      "options": [
        "Rellenar los detalles para obtener tu devolución",
        "Ignorarlo; el departamento de impuestos utiliza portales oficiales, no SMS",
        "Verificar si el número del remitente parece profesional"
      ],
      "correct_index": 1,
      "category": "personal_info",
      "explanation": "Las agencias gubernamentales nunca piden información sensible como PAN o detalles bancarios a través de SMS."
    },
    {
      "id": 10,
      "question": "¿Qué significa 'Vishing'?",
      "options": [
        "Phishing de voz (phishing a través de llamadas telefónicas)",
        "Phishing de video",
        "Phishing visual"
      ],
      "correct_index": 0,
      "category": "social_engineering",
      "explanation": "El vishing es phishing realizado a través de llamadas telefónicas para engañar a las personas para que den su información personal."
    },
    {
      "id": 11,
      "question": "Ves un enlace: 'https://paypаl.com' (con un carácter especial 'а'). ¿Qué ataque se llama esto?",
      "options": [
        "Ataque de carácter",
        "Ataque de homógrafo",
        "Intercambio de enlaces"
      ],
      "correct_index": 1,
      "category": "link_safety",
      "explanation": "Los ataques de homógrafo utilizan caracteres que se parecen a los de diferentes alfabetos para suplantar dominios."
    },
    {
      "id": 12,
      "question": "Un reclutador te contacta ofreciéndote un trabajo de 'trabajo desde casa' muy bien pagado que requiere un 'depósito de seguridad'. ¿Pagas?",
      "options": [
        "Sí, es un pequeño precio por un buen trabajo",
        "Sólo si me proporcionan un contrato primero",
        "No, las empresas reales nunca piden dinero para contratarte"
      ],
      "correct_index": 2,
      "category": "social_engineering",
      "explanation": "Los estafas de trabajo a menudo solicitan 'depósitos' por adelantado. Los empleadores reales te pagan a ti; tú no les pagas a ellos."
    },
    {
      "id": 13,
      "question": "Tu jefe te envía un correo electrónico urgente pidiéndote que compres tarjetas de regalo y envíes los códigos. ¿Qué deberías hacer?",
      "options": [
        "Llamar a mi jefe directamente para confirmar la solicitud",
        "Comprarlas de inmediato para mostrar eficiencia",
        "Pedir la tarjeta de crédito de la empresa primero"
      ],
      "correct_index": 0,
      "category": "social_engineering",
      "explanation": "Las solicitudes de tarjetas de regalo son estafas comunes de 'compromiso de correo electrónico empresarial'. Siempre verifica a través de otro canal."
    },
    {
      "id": 14,
      "question": "Una aplicación te pide permiso para leer todos tus mensajes de SMS. ¿Deberías permitirlo?",
      "options": [
        "Sí, muchas aplicaciones necesitan esto para los OTP",
        "No, podría robar tus OTP bancarios a medida que llegan",
        "Sólo si es de la Tienda de Aplicaciones"
      ],
      "correct_index": 1,
      "category": "personal_info",
      "explanation": "Las aplicaciones maliciosas utilizan permisos de SMS para 'husmear' y robar OTP bancarios."
    },
    {
      "id": 15,
      "question": "Si accidentalmente ingresaste tu contraseña en un sitio de phishing, ¿cuál es el primer paso crítico?",
      "options": [
        "Llamar a la policía",
        "Esperar y ver si sucede algo",
        "Cambiar tu contraseña de inmediato en el sitio real"
      ],
      "correct_index": 2,
      "category": "personal_info",
      "explanation": "La velocidad es clave. Cambiar tu contraseña de inmediato puede bloquear al atacante."
    }
  ]
}